{
"meta":{"test_sets":[],"test_metrics":[],"learn_metrics":[{"best_value":"Min","name":"Logloss"}],"launch_mode":"Train","parameters":"","iteration_count":1000,"learn_sets":["learn"],"name":"experiment"},
"iterations":[
{"learn":[0.6413986241],"iteration":0,"passed_time":0.02731264238,"remaining_time":27.28532973},
{"learn":[0.5937199557],"iteration":1,"passed_time":0.05217204023,"remaining_time":26.03384807},
{"learn":[0.5540640387],"iteration":2,"passed_time":0.07546673954,"remaining_time":25.08011311},
{"learn":[0.5239447102],"iteration":3,"passed_time":0.1010495713,"remaining_time":25.16134326},
{"learn":[0.4862922318],"iteration":4,"passed_time":0.12626275,"remaining_time":25.12628724},
{"learn":[0.4640730587],"iteration":5,"passed_time":0.1526490772,"remaining_time":25.28886378},
{"learn":[0.4471402449],"iteration":6,"passed_time":0.1785252457,"remaining_time":25.32508128},
{"learn":[0.420303567],"iteration":7,"passed_time":0.2044881639,"remaining_time":25.35653233},
{"learn":[0.396247379],"iteration":8,"passed_time":0.23145115,"remaining_time":25.48534329},
{"learn":[0.3855360898],"iteration":9,"passed_time":0.2552181229,"remaining_time":25.26659416},
{"learn":[0.3709103735],"iteration":10,"passed_time":0.2782251783,"remaining_time":25.01497285},
{"learn":[0.3529931196],"iteration":11,"passed_time":0.3016166604,"remaining_time":24.83310504},
{"learn":[0.341597372],"iteration":12,"passed_time":0.3252731733,"remaining_time":24.69574016},
{"learn":[0.3327917553],"iteration":13,"passed_time":0.349536207,"remaining_time":24.61733572},
{"learn":[0.3224016023],"iteration":14,"passed_time":0.3736906723,"remaining_time":24.53902082},
{"learn":[0.3123766249],"iteration":15,"passed_time":0.3979376143,"remaining_time":24.47316328},
{"learn":[0.3046861862],"iteration":16,"passed_time":0.4213753247,"remaining_time":24.36540848},
{"learn":[0.2976362614],"iteration":17,"passed_time":0.4461413031,"remaining_time":24.33948665},
{"learn":[0.2914775723],"iteration":18,"passed_time":0.4693058621,"remaining_time":24.23100267},
{"learn":[0.2828119975],"iteration":19,"passed_time":0.494439754,"remaining_time":24.22754795},
{"learn":[0.2766553302],"iteration":20,"passed_time":0.5190063007,"remaining_time":24.19557945},
{"learn":[0.2700949583],"iteration":21,"passed_time":0.5432503393,"remaining_time":24.1499469},
{"learn":[0.2644103705],"iteration":22,"passed_time":0.5692132379,"remaining_time":24.17918841},
{"learn":[0.2599727706],"iteration":23,"passed_time":0.5955215825,"remaining_time":24.21787769},
{"learn":[0.2547894322],"iteration":24,"passed_time":0.6197793324,"remaining_time":24.17139396},
{"learn":[0.2516291105],"iteration":25,"passed_time":0.6436067208,"remaining_time":24.11049793},
{"learn":[0.2420113621],"iteration":26,"passed_time":0.6695237143,"remaining_time":24.12765089},
{"learn":[0.2391889679],"iteration":27,"passed_time":0.6944561594,"remaining_time":24.10754953},
{"learn":[0.2371823183],"iteration":28,"passed_time":0.7185735008,"remaining_time":24.05982308},
{"learn":[0.2319369973],"iteration":29,"passed_time":0.742758339,"remaining_time":24.01585296},
{"learn":[0.2290535983],"iteration":30,"passed_time":0.7698433291,"remaining_time":24.06381245},
{"learn":[0.2239112312],"iteration":31,"passed_time":0.7938256373,"remaining_time":24.01322553},
{"learn":[0.2171600773],"iteration":32,"passed_time":0.8173412357,"remaining_time":23.950575},
{"learn":[0.2122496245],"iteration":33,"passed_time":0.842516273,"remaining_time":23.93737411},
{"learn":[0.2079953843],"iteration":34,"passed_time":0.8668727425,"remaining_time":23.9009199},
{"learn":[0.2066150051],"iteration":35,"passed_time":0.8899256489,"remaining_time":23.83023126},
{"learn":[0.2042216118],"iteration":36,"passed_time":0.9154518259,"remaining_time":23.82648941},
{"learn":[0.2010678027],"iteration":37,"passed_time":0.9404394536,"remaining_time":23.80796722},
{"learn":[0.1978945373],"iteration":38,"passed_time":0.9637547662,"remaining_time":23.7479059},
{"learn":[0.1955846656],"iteration":39,"passed_time":0.9863842166,"remaining_time":23.6732212},
{"learn":[0.1928883973],"iteration":40,"passed_time":1.010919249,"remaining_time":23.6456478},
{"learn":[0.1910779833],"iteration":41,"passed_time":1.03417898,"remaining_time":23.58913008},
{"learn":[0.1893447958],"iteration":42,"passed_time":1.055895264,"remaining_time":23.49980854},
{"learn":[0.1875234575],"iteration":43,"passed_time":1.080752431,"remaining_time":23.48180283},
{"learn":[0.1857206982],"iteration":44,"passed_time":1.104045483,"remaining_time":23.43029858},
{"learn":[0.1848708016],"iteration":45,"passed_time":1.126996681,"remaining_time":23.37293116},
{"learn":[0.1837492985],"iteration":46,"passed_time":1.155025762,"remaining_time":23.41999046},
{"learn":[0.1812839689],"iteration":47,"passed_time":1.180399145,"remaining_time":23.41124972},
{"learn":[0.1805342116],"iteration":48,"passed_time":1.202850253,"remaining_time":23.3451141},
{"learn":[0.1789945477],"iteration":49,"passed_time":1.224804084,"remaining_time":23.2712776},
{"learn":[0.1777374727],"iteration":50,"passed_time":1.24896273,"remaining_time":23.24050256},
{"learn":[0.1767554195],"iteration":51,"passed_time":1.273612733,"remaining_time":23.21893982},
{"learn":[0.1760310344],"iteration":52,"passed_time":1.297647268,"remaining_time":23.18626346},
{"learn":[0.1750769599],"iteration":53,"passed_time":1.320965891,"remaining_time":23.14136542},
{"learn":[0.1743409949],"iteration":54,"passed_time":1.347218929,"remaining_time":23.14767069},
{"learn":[0.1734994184],"iteration":55,"passed_time":1.370752167,"remaining_time":23.1069651},
{"learn":[0.1723384984],"iteration":56,"passed_time":1.394361404,"remaining_time":23.06811936},
{"learn":[0.1707820256],"iteration":57,"passed_time":1.417994367,"remaining_time":23.03018438},
{"learn":[0.1696781924],"iteration":58,"passed_time":1.441776689,"remaining_time":22.99511635},
{"learn":[0.1689677243],"iteration":59,"passed_time":1.465262381,"remaining_time":22.95577731},
{"learn":[0.1684610813],"iteration":60,"passed_time":1.488713338,"remaining_time":22.91642334},
{"learn":[0.1675995685],"iteration":61,"passed_time":1.514769601,"remaining_time":22.91699815},
{"learn":[0.1668956817],"iteration":62,"passed_time":1.540435955,"remaining_time":22.91092841},
{"learn":[0.166460105],"iteration":63,"passed_time":1.563081472,"remaining_time":22.86006653},
{"learn":[0.1657838058],"iteration":64,"passed_time":1.586502297,"remaining_time":22.82122536},
{"learn":[0.1649905144],"iteration":65,"passed_time":1.610411546,"remaining_time":22.7897634},
{"learn":[0.1646112188],"iteration":66,"passed_time":1.635381914,"remaining_time":22.77330337},
{"learn":[0.1641964081],"iteration":67,"passed_time":1.65969594,"remaining_time":22.7475973},
{"learn":[0.1637387629],"iteration":68,"passed_time":1.683728686,"remaining_time":22.71813633},
{"learn":[0.1629262938],"iteration":69,"passed_time":1.710470241,"remaining_time":22.72481892},
{"learn":[0.1623808302],"iteration":70,"passed_time":1.736789469,"remaining_time":22.72503403},
{"learn":[0.1620384388],"iteration":71,"passed_time":1.760092006,"remaining_time":22.68563029},
{"learn":[0.1615952337],"iteration":72,"passed_time":1.784852771,"remaining_time":22.66518518},
{"learn":[0.1611029483],"iteration":73,"passed_time":1.810169195,"remaining_time":22.65157668},
{"learn":[0.1605952733],"iteration":74,"passed_time":1.836916944,"remaining_time":22.65530898},
{"learn":[0.1602237171],"iteration":75,"passed_time":1.860932963,"remaining_time":22.62502708},
{"learn":[0.1596321927],"iteration":76,"passed_time":1.885521342,"remaining_time":22.60176882},
{"learn":[0.1591196978],"iteration":77,"passed_time":1.911565531,"remaining_time":22.59568486},
{"learn":[0.158625443],"iteration":78,"passed_time":1.937609617,"remaining_time":22.58909439},
{"learn":[0.1582199529],"iteration":79,"passed_time":1.961083176,"remaining_time":22.55245652},
{"learn":[0.1577711826],"iteration":80,"passed_time":1.985311916,"remaining_time":22.52471174},
{"learn":[0.1574082927],"iteration":81,"passed_time":2.011906455,"remaining_time":22.52353811},
{"learn":[0.157181217],"iteration":82,"passed_time":2.0376448,"remaining_time":22.51229255},
{"learn":[0.1569157672],"iteration":83,"passed_time":2.060393399,"remaining_time":22.46809945},
{"learn":[0.1566191492],"iteration":84,"passed_time":2.083895519,"remaining_time":22.43252235},
{"learn":[0.1558658132],"iteration":85,"passed_time":2.109303332,"remaining_time":22.4174796},
{"learn":[0.1554278544],"iteration":86,"passed_time":2.138941771,"remaining_time":22.44659583},
{"learn":[0.1550044099],"iteration":87,"passed_time":2.162433275,"remaining_time":22.41067212},
{"learn":[0.1540440503],"iteration":88,"passed_time":2.186742229,"remaining_time":22.38339517},
{"learn":[0.1538083448],"iteration":89,"passed_time":2.212334291,"remaining_time":22.36915783},
{"learn":[0.1535078693],"iteration":90,"passed_time":2.237277324,"remaining_time":22.34818778},
{"learn":[0.153255665],"iteration":91,"passed_time":2.262917586,"remaining_time":22.3340127},
{"learn":[0.1528650581],"iteration":92,"passed_time":2.287872155,"remaining_time":22.3129037},
{"learn":[0.1525707158],"iteration":93,"passed_time":2.312591223,"remaining_time":22.28944306},
{"learn":[0.152155405],"iteration":94,"passed_time":2.33556484,"remaining_time":22.24932821},
{"learn":[0.1518184741],"iteration":95,"passed_time":2.359427738,"remaining_time":22.21794454},
{"learn":[0.1513948292],"iteration":96,"passed_time":2.382040208,"remaining_time":22.17507534},
{"learn":[0.1505307675],"iteration":97,"passed_time":2.407354366,"remaining_time":22.1574861},
{"learn":[0.1500251983],"iteration":98,"passed_time":2.431089486,"remaining_time":22.12536997},
{"learn":[0.1497086661],"iteration":99,"passed_time":2.455845434,"remaining_time":22.1026089},
{"learn":[0.149346354],"iteration":100,"passed_time":2.480541846,"remaining_time":22.07927841},
{"learn":[0.1490273686],"iteration":101,"passed_time":2.505553416,"remaining_time":22.05869576},
{"learn":[0.1487677745],"iteration":102,"passed_time":2.532279689,"remaining_time":22.05296001},
{"learn":[0.1485274202],"iteration":103,"passed_time":2.558311521,"remaining_time":22.04083772},
{"learn":[0.1479499352],"iteration":104,"passed_time":2.581342873,"remaining_time":22.00287496},
{"learn":[0.1477706623],"iteration":105,"passed_time":2.603961948,"remaining_time":21.96171681},
{"learn":[0.1475659988],"iteration":106,"passed_time":2.625297662,"remaining_time":21.91019451},
{"learn":[0.1473148827],"iteration":107,"passed_time":2.648304616,"remaining_time":21.87303442},
{"learn":[0.1470689024],"iteration":108,"passed_time":2.673395318,"remaining_time":21.85316723},
{"learn":[0.1468399596],"iteration":109,"passed_time":2.697921884,"remaining_time":21.8286407},
{"learn":[0.1464710129],"iteration":110,"passed_time":2.722998977,"remaining_time":21.80852334},
{"learn":[0.1462820676],"iteration":111,"passed_time":2.747159568,"remaining_time":21.78105086},
{"learn":[0.1460243097],"iteration":112,"passed_time":2.770683131,"remaining_time":21.74863661},
{"learn":[0.1455259227],"iteration":113,"passed_time":2.793450272,"remaining_time":21.71049948},
{"learn":[0.1453238048],"iteration":114,"passed_time":2.81934782,"remaining_time":21.69672018},
{"learn":[0.1450308858],"iteration":115,"passed_time":2.844949257,"remaining_time":21.68047537},
{"learn":[0.1446771961],"iteration":116,"passed_time":2.871440705,"remaining_time":21.67078754},
{"learn":[0.1444189612],"iteration":117,"passed_time":2.897234965,"remaining_time":21.65560373},
{"learn":[0.1442503423],"iteration":118,"passed_time":2.92131228,"remaining_time":21.62753041},
{"learn":[0.1440470215],"iteration":119,"passed_time":2.944989522,"remaining_time":21.59658983},
{"learn":[0.1439121962],"iteration":120,"passed_time":2.968291309,"remaining_time":21.56304183},
{"learn":[0.1436414164],"iteration":121,"passed_time":2.993117438,"remaining_time":21.54063205},
{"learn":[0.1434324874],"iteration":122,"passed_time":3.016150417,"remaining_time":21.50539769},
{"learn":[0.1432830338],"iteration":123,"passed_time":3.039018868,"remaining_time":21.46919781},
{"learn":[0.1430611315],"iteration":124,"passed_time":3.062614157,"remaining_time":21.4382991},
{"learn":[0.1426829582],"iteration":125,"passed_time":3.085782642,"remaining_time":21.40455579},
{"learn":[0.1423947026],"iteration":126,"passed_time":3.108339415,"remaining_time":21.36677409},
{"learn":[0.1422478649],"iteration":127,"passed_time":3.132879231,"remaining_time":21.34273976},
{"learn":[0.1420717871],"iteration":128,"passed_time":3.157793142,"remaining_time":21.32122346},
{"learn":[0.1417082318],"iteration":129,"passed_time":3.180156062,"remaining_time":21.28258288},
{"learn":[0.1415817529],"iteration":130,"passed_time":3.202366891,"remaining_time":21.2431819},
{"learn":[0.1414310361],"iteration":131,"passed_time":3.227534741,"remaining_time":21.22348602},
{"learn":[0.1410355706],"iteration":132,"passed_time":3.251802492,"remaining_time":21.19784031},
{"learn":[0.140832849],"iteration":133,"passed_time":3.276183032,"remaining_time":21.17294407},
{"learn":[0.1405905775],"iteration":134,"passed_time":3.302465552,"remaining_time":21.16024224},
{"learn":[0.1404046385],"iteration":135,"passed_time":3.325410032,"remaining_time":21.12613432},
{"learn":[0.1401832956],"iteration":136,"passed_time":3.348907632,"remaining_time":21.09567362},
{"learn":[0.139828862],"iteration":137,"passed_time":3.372525441,"remaining_time":21.06606471},
{"learn":[0.1394131831],"iteration":138,"passed_time":3.395668975,"remaining_time":21.03360423},
{"learn":[0.1388268278],"iteration":139,"passed_time":3.419615848,"remaining_time":21.00621164},
{"learn":[0.1386052117],"iteration":140,"passed_time":3.443269661,"remaining_time":20.97708255},
{"learn":[0.1378721716],"iteration":141,"passed_time":3.465596704,"remaining_time":20.94001389},
{"learn":[0.1377312804],"iteration":142,"passed_time":3.488056656,"remaining_time":20.90394793},
{"learn":[0.137520885],"iteration":143,"passed_time":3.511706166,"remaining_time":20.87514221},
{"learn":[0.1373158534],"iteration":144,"passed_time":3.537064488,"remaining_time":20.8564837},
{"learn":[0.1370738209],"iteration":145,"passed_time":3.563397304,"remaining_time":20.84343355},
{"learn":[0.1368860799],"iteration":146,"passed_time":3.58879433,"remaining_time":20.82477254},
{"learn":[0.1365792005],"iteration":147,"passed_time":3.613348917,"remaining_time":20.80117079},
{"learn":[0.1364046332],"iteration":148,"passed_time":3.638882868,"remaining_time":20.7831498},
{"learn":[0.1360839658],"iteration":149,"passed_time":3.66277206,"remaining_time":20.75570834},
{"learn":[0.1358897154],"iteration":150,"passed_time":3.68647658,"remaining_time":20.7272756},
{"learn":[0.1356270074],"iteration":151,"passed_time":3.711134242,"remaining_time":20.70422261},
{"learn":[0.1354063945],"iteration":152,"passed_time":3.735881416,"remaining_time":20.68164418},
{"learn":[0.1352506342],"iteration":153,"passed_time":3.75855725,"remaining_time":20.64765866},
{"learn":[0.1350535105],"iteration":154,"passed_time":3.78184165,"remaining_time":20.61713674},
{"learn":[0.1347793525],"iteration":155,"passed_time":3.804615496,"remaining_time":20.58394538},
{"learn":[0.1346087376],"iteration":156,"passed_time":3.830623677,"remaining_time":20.56825325},
{"learn":[0.1343613174],"iteration":157,"passed_time":3.853452138,"remaining_time":20.53548544},
{"learn":[0.134131115],"iteration":158,"passed_time":3.878309718,"remaining_time":20.5135753},
{"learn":[0.1337356776],"iteration":159,"passed_time":3.900583761,"remaining_time":20.47806475},
{"learn":[0.1335248339],"iteration":160,"passed_time":3.922332765,"remaining_time":20.43998255},
{"learn":[0.133265051],"iteration":161,"passed_time":3.946344644,"remaining_time":20.41380748},
{"learn":[0.1329641328],"iteration":162,"passed_time":3.972652291,"remaining_time":20.39944765},
{"learn":[0.1328034169],"iteration":163,"passed_time":3.997847494,"remaining_time":20.37927137},
{"learn":[0.1326771999],"iteration":164,"passed_time":4.021381738,"remaining_time":20.3506288},
{"learn":[0.1325223056],"iteration":165,"passed_time":4.044538485,"remaining_time":20.32015118},
{"learn":[0.1321529703],"iteration":166,"passed_time":4.069630683,"remaining_time":20.29941532},
{"learn":[0.1319835987],"iteration":167,"passed_time":4.092711232,"remaining_time":20.26866515},
{"learn":[0.131861944],"iteration":168,"passed_time":4.116383661,"remaining_time":20.24091611},
{"learn":[0.1316929383],"iteration":169,"passed_time":4.139992704,"remaining_time":20.21290555},
{"learn":[0.1315131561],"iteration":170,"passed_time":4.166301663,"remaining_time":20.19803555},
{"learn":[0.131415421],"iteration":171,"passed_time":4.18922545,"remaining_time":20.16673647},
{"learn":[0.1313016239],"iteration":172,"passed_time":4.212109788,"remaining_time":20.13534564},
{"learn":[0.1311129423],"iteration":173,"passed_time":4.238886466,"remaining_time":20.12253001},
{"learn":[0.1309355016],"iteration":174,"passed_time":4.263951602,"remaining_time":20.10148612},
{"learn":[0.1307994304],"iteration":175,"passed_time":4.28940828,"remaining_time":20.08222968},
{"learn":[0.1305610785],"iteration":176,"passed_time":4.313506054,"remaining_time":20.05658465},
{"learn":[0.1304134237],"iteration":177,"passed_time":4.336795154,"remaining_time":20.02722257},
{"learn":[0.1298949768],"iteration":178,"passed_time":4.361272576,"remaining_time":20.00337869},
{"learn":[0.1298017638],"iteration":179,"passed_time":4.387263671,"remaining_time":19.98642339},
{"learn":[0.1294583056],"iteration":180,"passed_time":4.411821816,"remaining_time":19.96288435},
{"learn":[0.1292727895],"iteration":181,"passed_time":4.437481886,"remaining_time":19.94428672},
{"learn":[0.1291035674],"iteration":182,"passed_time":4.461745948,"remaining_time":19.91937945},
{"learn":[0.1289172961],"iteration":183,"passed_time":4.486277312,"remaining_time":19.8956646},
{"learn":[0.128647504],"iteration":184,"passed_time":4.510839194,"remaining_time":19.87207537},
{"learn":[0.1284596247],"iteration":185,"passed_time":4.538804084,"remaining_time":19.86336841},
{"learn":[0.1282421876],"iteration":186,"passed_time":4.567806917,"remaining_time":19.85896804},
{"learn":[0.1279952509],"iteration":187,"passed_time":4.591915655,"remaining_time":19.83316761},
{"learn":[0.1274608621],"iteration":188,"passed_time":4.61478525,"remaining_time":19.80206793},
{"learn":[0.1273472524],"iteration":189,"passed_time":4.636959591,"remaining_time":19.76809089},
{"learn":[0.1270317326],"iteration":190,"passed_time":4.661828858,"remaining_time":19.74565207},
{"learn":[0.1268887055],"iteration":191,"passed_time":4.685527077,"remaining_time":19.71825978},
{"learn":[0.126732528],"iteration":192,"passed_time":4.709995135,"remaining_time":19.69412473},
{"learn":[0.1264921088],"iteration":193,"passed_time":4.733522964,"remaining_time":19.66607995},
{"learn":[0.126343686],"iteration":194,"passed_time":4.758998159,"remaining_time":19.6461206},
{"learn":[0.1261795513],"iteration":195,"passed_time":4.781892485,"remaining_time":19.61551815},
{"learn":[0.1257098645],"iteration":196,"passed_time":4.804696456,"remaining_time":19.58462566},
{"learn":[0.1254734766],"iteration":197,"passed_time":4.82682382,"remaining_time":19.55107426},
{"learn":[0.1253220703],"iteration":198,"passed_time":4.851026642,"remaining_time":19.52599166},
{"learn":[0.1248805916],"iteration":199,"passed_time":4.874786994,"remaining_time":19.49914798},
{"learn":[0.1246231577],"iteration":200,"passed_time":4.899264469,"remaining_time":19.47518563},
{"learn":[0.1244906621],"iteration":201,"passed_time":4.924127206,"remaining_time":19.45274015},
{"learn":[0.1243906063],"iteration":202,"passed_time":4.946178783,"remaining_time":19.41923394},
{"learn":[0.1242806258],"iteration":203,"passed_time":4.969350965,"remaining_time":19.39021259},
{"learn":[0.1241283571],"iteration":204,"passed_time":4.994179039,"remaining_time":19.36766993},
{"learn":[0.1240131225],"iteration":205,"passed_time":5.016245698,"remaining_time":19.33446158},
{"learn":[0.1239012185],"iteration":206,"passed_time":5.039477765,"remaining_time":19.30582545},
{"learn":[0.1237134405],"iteration":207,"passed_time":5.061885097,"remaining_time":19.27410095},
{"learn":[0.1234884499],"iteration":208,"passed_time":5.08586843,"remaining_time":19.24843028},
{"learn":[0.1233850828],"iteration":209,"passed_time":5.10973376,"remaining_time":19.22233177},
{"learn":[0.1232417486],"iteration":210,"passed_time":5.134754654,"remaining_time":19.20057546},
{"learn":[0.1230590241],"iteration":211,"passed_time":5.158454819,"remaining_time":19.17387923},
{"learn":[0.1229243092],"iteration":212,"passed_time":5.181293533,"remaining_time":19.14402822},
{"learn":[0.1227883456],"iteration":213,"passed_time":5.205271415,"remaining_time":19.11842679},
{"learn":[0.1226801179],"iteration":214,"passed_time":5.227183226,"remaining_time":19.0852969},
{"learn":[0.1225736354],"iteration":215,"passed_time":5.25120583,"remaining_time":19.05993227},
{"learn":[0.1224047224],"iteration":216,"passed_time":5.275127984,"remaining_time":19.03421757},
{"learn":[0.1222142213],"iteration":217,"passed_time":5.300760187,"remaining_time":19.01465351},
{"learn":[0.1220862802],"iteration":218,"passed_time":5.3241565,"remaining_time":18.98706039},
{"learn":[0.1219013497],"iteration":219,"passed_time":5.349091127,"remaining_time":18.96495945},
{"learn":[0.1215304262],"iteration":220,"passed_time":5.373992204,"remaining_time":18.9427146},
{"learn":[0.1214063284],"iteration":221,"passed_time":5.399208441,"remaining_time":18.9215503},
{"learn":[0.1212039624],"iteration":222,"passed_time":5.424223506,"remaining_time":18.89964872},
{"learn":[0.1211063876],"iteration":223,"passed_time":5.449845245,"remaining_time":18.87982103},
{"learn":[0.1208514223],"iteration":224,"passed_time":5.473140062,"remaining_time":18.85192688},
{"learn":[0.1207064195],"iteration":225,"passed_time":5.496060737,"remaining_time":18.82279208},
{"learn":[0.1202023752],"iteration":226,"passed_time":5.521058158,"remaining_time":18.80078395},
{"learn":[0.1200175462],"iteration":227,"passed_time":5.54451029,"remaining_time":18.7735173},
{"learn":[0.1198916781],"iteration":228,"passed_time":5.569855158,"remaining_time":18.75265645},
{"learn":[0.1197411039],"iteration":229,"passed_time":5.595008698,"remaining_time":18.73111608},
{"learn":[0.1196353056],"iteration":230,"passed_time":5.617101022,"remaining_time":18.69935362},
{"learn":[0.1194320512],"iteration":231,"passed_time":5.640890278,"remaining_time":18.67329196},
{"learn":[0.1193119046],"iteration":232,"passed_time":5.667130118,"remaining_time":18.65531674},
{"learn":[0.1191230539],"iteration":233,"passed_time":5.691392694,"remaining_time":18.63079831},
{"learn":[0.1189260315],"iteration":234,"passed_time":5.715712739,"remaining_time":18.60646913},
{"learn":[0.1185196193],"iteration":235,"passed_time":5.740465297,"remaining_time":18.5835402},
{"learn":[0.1184143717],"iteration":236,"passed_time":5.764679506,"remaining_time":18.55886271},
{"learn":[0.1182627367],"iteration":237,"passed_time":5.787875418,"remaining_time":18.53092886},
{"learn":[0.1181543819],"iteration":238,"passed_time":5.810253879,"remaining_time":18.50043181},
{"learn":[0.1180304888],"iteration":239,"passed_time":5.83309726,"remaining_time":18.47147466},
{"learn":[0.1179205892],"iteration":240,"passed_time":5.857687874,"remaining_time":18.44807094},
{"learn":[0.1175114947],"iteration":241,"passed_time":5.881045539,"remaining_time":18.42079553},
{"learn":[0.1172783217],"iteration":242,"passed_time":5.907062955,"remaining_time":18.40183809},
{"learn":[0.1166932757],"iteration":243,"passed_time":5.930347398,"remaining_time":18.37435505},
{"learn":[0.1165672455],"iteration":244,"passed_time":5.955765376,"remaining_time":18.35348106},
{"learn":[0.1164156388],"iteration":245,"passed_time":5.978998718,"remaining_time":18.32587412},
{"learn":[0.1162800301],"iteration":246,"passed_time":6.002439925,"remaining_time":18.29893629},
{"learn":[0.1161450933],"iteration":247,"passed_time":6.025357236,"remaining_time":18.27043807},
{"learn":[0.11599744],"iteration":248,"passed_time":6.050448054,"remaining_time":18.24854012},
{"learn":[0.115664047],"iteration":249,"passed_time":6.076227755,"remaining_time":18.22868326},
{"learn":[0.1154961937],"iteration":250,"passed_time":6.098603606,"remaining_time":18.19862192},
{"learn":[0.1154189934],"iteration":251,"passed_time":6.123089545,"remaining_time":18.17488484},
{"learn":[0.1152713805],"iteration":252,"passed_time":6.146421989,"remaining_time":18.14773607},
{"learn":[0.1151403404],"iteration":253,"passed_time":6.170711039,"remaining_time":18.12342691},
{"learn":[0.1150195707],"iteration":254,"passed_time":6.195623546,"remaining_time":18.10093938},
{"learn":[0.1148958397],"iteration":255,"passed_time":6.217158778,"remaining_time":18.0686177},
{"learn":[0.1147601174],"iteration":256,"passed_time":6.241014036,"remaining_time":18.04308727},
{"learn":[0.1146392166],"iteration":257,"passed_time":6.265830568,"remaining_time":18.02033443},
{"learn":[0.1145338854],"iteration":258,"passed_time":6.28845275,"remaining_time":17.9912876},
{"learn":[0.1143876558],"iteration":259,"passed_time":6.312916384,"remaining_time":17.96753125},
{"learn":[0.1141703971],"iteration":260,"passed_time":6.336955289,"remaining_time":17.94256689},
{"learn":[0.1140372814],"iteration":261,"passed_time":6.361798656,"remaining_time":17.9198756},
{"learn":[0.1138989307],"iteration":262,"passed_time":6.387167442,"remaining_time":17.89864032},
{"learn":[0.1136693443],"iteration":263,"passed_time":6.412757961,"remaining_time":17.87799189},
{"learn":[0.113540788],"iteration":264,"passed_time":6.437383738,"remaining_time":17.85463037},
{"learn":[0.1134136389],"iteration":265,"passed_time":6.462157895,"remaining_time":17.83166878},
{"learn":[0.1132692897],"iteration":266,"passed_time":6.487457238,"remaining_time":17.81013541},
{"learn":[0.1131537386],"iteration":267,"passed_time":6.51246481,"remaining_time":17.78777702},
{"learn":[0.1130167999],"iteration":268,"passed_time":6.537771881,"remaining_time":17.76621281},
{"learn":[0.1129133533],"iteration":269,"passed_time":6.562462381,"remaining_time":17.74295384},
{"learn":[0.1128330809],"iteration":270,"passed_time":6.587287934,"remaining_time":17.72004761},
{"learn":[0.1126730361],"iteration":271,"passed_time":6.613039968,"remaining_time":17.69960697},
{"learn":[0.1125535891],"iteration":272,"passed_time":6.63881947,"remaining_time":17.67920057},
{"learn":[0.1124433873],"iteration":273,"passed_time":6.662080762,"remaining_time":17.6520826},
{"learn":[0.1122712396],"iteration":274,"passed_time":6.687629395,"remaining_time":17.63102295},
{"learn":[0.1121611884],"iteration":275,"passed_time":6.711642318,"remaining_time":17.60590231},
{"learn":[0.112016716],"iteration":276,"passed_time":6.737112662,"remaining_time":17.5845937},
{"learn":[0.1119147234],"iteration":277,"passed_time":6.76071771,"remaining_time":17.55841074},
{"learn":[0.1117524264],"iteration":278,"passed_time":6.784378993,"remaining_time":17.53239159},
{"learn":[0.1116429062],"iteration":279,"passed_time":6.809386779,"remaining_time":17.50985172},
{"learn":[0.1115139162],"iteration":280,"passed_time":6.835137095,"remaining_time":17.48919421},
{"learn":[0.1113946811],"iteration":281,"passed_time":6.862363995,"remaining_time":17.4722601},
{"learn":[0.1112597992],"iteration":282,"passed_time":6.887326325,"remaining_time":17.44951581},
{"learn":[0.1110851856],"iteration":283,"passed_time":6.912321172,"remaining_time":17.42683788},
{"learn":[0.1109683434],"iteration":284,"passed_time":6.938206739,"remaining_time":17.40637831},
{"learn":[0.11082254],"iteration":285,"passed_time":6.963861884,"remaining_time":17.38530554},
{"learn":[0.1106475148],"iteration":286,"passed_time":6.988738852,"remaining_time":17.3622676},
{"learn":[0.1104185035],"iteration":287,"passed_time":7.011727566,"remaining_time":17.33454871},
{"learn":[0.1102729393],"iteration":288,"passed_time":7.034985955,"remaining_time":17.307526},
{"learn":[0.1100177104],"iteration":289,"passed_time":7.058956668,"remaining_time":17.28227322},
{"learn":[0.1098438512],"iteration":290,"passed_time":7.082644702,"remaining_time":17.25634053},
{"learn":[0.1096676771],"iteration":291,"passed_time":7.104575751,"remaining_time":17.22616312},
{"learn":[0.1095592015],"iteration":292,"passed_time":7.129074819,"remaining_time":17.20223856},
{"learn":[0.1094662416],"iteration":293,"passed_time":7.151199721,"remaining_time":17.17260885},
{"learn":[0.1093629408],"iteration":294,"passed_time":7.176213412,"remaining_time":17.14993375},
{"learn":[0.1092208186],"iteration":295,"passed_time":7.202507829,"remaining_time":17.13028889},
{"learn":[0.109121692],"iteration":296,"passed_time":7.226239286,"remaining_time":17.10453272},
{"learn":[0.1090155793],"iteration":297,"passed_time":7.251406908,"remaining_time":17.08217332},
{"learn":[0.1089538505],"iteration":298,"passed_time":7.27402588,"remaining_time":17.05381987},
{"learn":[0.1088352305],"iteration":299,"passed_time":7.296318844,"remaining_time":17.02474397},
{"learn":[0.1087260907],"iteration":300,"passed_time":7.322066212,"remaining_time":17.00373516},
{"learn":[0.1086163503],"iteration":301,"passed_time":7.345950491,"remaining_time":16.97838888},
{"learn":[0.1084939694],"iteration":302,"passed_time":7.369731007,"remaining_time":16.95281357},
{"learn":[0.1083942463],"iteration":303,"passed_time":7.394577187,"remaining_time":16.92968988},
{"learn":[0.1082683822],"iteration":304,"passed_time":7.41845566,"remaining_time":16.90434978},
{"learn":[0.1081883422],"iteration":305,"passed_time":7.443652545,"remaining_time":16.88200937},
{"learn":[0.1080697137],"iteration":306,"passed_time":7.466665604,"remaining_time":16.85472073},
{"learn":[0.107970989],"iteration":307,"passed_time":7.491640022,"remaining_time":16.83186654},
{"learn":[0.1078340462],"iteration":308,"passed_time":7.516567851,"remaining_time":16.80889445},
{"learn":[0.107590278],"iteration":309,"passed_time":7.54207678,"remaining_time":16.78720316},
{"learn":[0.1074990531],"iteration":310,"passed_time":7.565556296,"remaining_time":16.76099128},
{"learn":[0.1074121086],"iteration":311,"passed_time":7.589580182,"remaining_time":16.73599732},
{"learn":[0.1072883319],"iteration":312,"passed_time":7.61385978,"remaining_time":16.71157083},
{"learn":[0.1071859278],"iteration":313,"passed_time":7.638728681,"remaining_time":16.68843272},
{"learn":[0.1070930141],"iteration":314,"passed_time":7.663918729,"remaining_time":16.665982},
{"learn":[0.1069648758],"iteration":315,"passed_time":7.687805976,"remaining_time":16.64069395},
{"learn":[0.1068296249],"iteration":316,"passed_time":7.710800974,"remaining_time":16.61349232},
{"learn":[0.1067462638],"iteration":317,"passed_time":7.735577952,"remaining_time":16.59013888},
{"learn":[0.1066539777],"iteration":318,"passed_time":7.760230019,"remaining_time":16.56650985},
{"learn":[0.1065417702],"iteration":319,"passed_time":7.784088743,"remaining_time":16.54118858},
{"learn":[0.1064690513],"iteration":320,"passed_time":7.808455365,"remaining_time":16.51695076},
{"learn":[0.1063607203],"iteration":321,"passed_time":7.833483995,"remaining_time":16.49410605},
{"learn":[0.1062677966],"iteration":322,"passed_time":7.856967952,"remaining_time":16.46801023},
{"learn":[0.1061756055],"iteration":323,"passed_time":7.879848185,"remaining_time":16.44067091},
{"learn":[0.1060408212],"iteration":324,"passed_time":7.905848096,"remaining_time":16.41983835},
{"learn":[0.1059106508],"iteration":325,"passed_time":7.929810547,"remaining_time":16.39476168},
{"learn":[0.1057909764],"iteration":326,"passed_time":7.952465588,"remaining_time":16.36700104},
{"learn":[0.1056813184],"iteration":327,"passed_time":7.977948238,"remaining_time":16.34506468},
{"learn":[0.1055435065],"iteration":328,"passed_time":8.003216254,"remaining_time":16.32266902},
{"learn":[0.1054160793],"iteration":329,"passed_time":8.02927615,"remaining_time":16.3018637},
{"learn":[0.1053297674],"iteration":330,"passed_time":8.054389816,"remaining_time":16.27911416},
{"learn":[0.105201553],"iteration":331,"passed_time":8.078443066,"remaining_time":16.25421677},
{"learn":[0.105074593],"iteration":332,"passed_time":8.104579827,"remaining_time":16.23349773},
{"learn":[0.1049762864],"iteration":333,"passed_time":8.130572768,"remaining_time":16.21245947},
{"learn":[0.1048671141],"iteration":334,"passed_time":8.156781006,"remaining_time":16.19181901},
{"learn":[0.1046779434],"iteration":335,"passed_time":8.184232971,"remaining_time":16.17360325},
{"learn":[0.1045129785],"iteration":336,"passed_time":8.20877528,"remaining_time":16.14960834},
{"learn":[0.104444232],"iteration":337,"passed_time":8.234029828,"remaining_time":16.12700517},
{"learn":[0.1044042349],"iteration":338,"passed_time":8.25719251,"remaining_time":16.10030752},
{"learn":[0.1043049099],"iteration":339,"passed_time":8.281758164,"remaining_time":16.07635408},
{"learn":[0.1041963847],"iteration":340,"passed_time":8.308368961,"remaining_time":16.0563494},
{"learn":[0.1041097676],"iteration":341,"passed_time":8.33293868,"remaining_time":16.0323791},
{"learn":[0.1039958842],"iteration":342,"passed_time":8.355134924,"remaining_time":16.00385902},
{"learn":[0.1039061119],"iteration":343,"passed_time":8.37968682,"remaining_time":15.97986789},
{"learn":[0.1037271253],"iteration":344,"passed_time":8.402640948,"remaining_time":15.95284006},
{"learn":[0.1035654504],"iteration":345,"passed_time":8.425383849,"remaining_time":15.92543652},
{"learn":[0.1034026787],"iteration":346,"passed_time":8.449216841,"remaining_time":15.90011123},
{"learn":[0.1033328335],"iteration":347,"passed_time":8.472997901,"remaining_time":15.87469722},
{"learn":[0.1032340759],"iteration":348,"passed_time":8.496087649,"remaining_time":15.84800304},
{"learn":[0.1031460931],"iteration":349,"passed_time":8.519727794,"remaining_time":15.82235162},
{"learn":[0.1030075861],"iteration":350,"passed_time":8.541709739,"remaining_time":15.79364564},
{"learn":[0.102899277],"iteration":351,"passed_time":8.566196342,"remaining_time":15.76958872},
{"learn":[0.102801921],"iteration":352,"passed_time":8.59119175,"remaining_time":15.74646193},
{"learn":[0.1027276044],"iteration":353,"passed_time":8.61473422,"remaining_time":15.72067318},
{"learn":[0.1025819884],"iteration":354,"passed_time":8.63886769,"remaining_time":15.69597087},
{"learn":[0.1024840095],"iteration":355,"passed_time":8.663060391,"remaining_time":15.67137891},
{"learn":[0.1023923407],"iteration":356,"passed_time":8.687436983,"remaining_time":15.64712039},
{"learn":[0.1022908402],"iteration":357,"passed_time":8.713005455,"remaining_time":15.62499861},
{"learn":[0.1021394121],"iteration":358,"passed_time":8.738014145,"remaining_time":15.60185813},
{"learn":[0.1020151039],"iteration":359,"passed_time":8.762281498,"remaining_time":15.57738933},
{"learn":[0.1018786547],"iteration":360,"passed_time":8.789797986,"remaining_time":15.55867289},
{"learn":[0.1017844986],"iteration":361,"passed_time":8.814495133,"remaining_time":15.53493894},
{"learn":[0.1016804817],"iteration":362,"passed_time":8.838880573,"remaining_time":15.51065269},
{"learn":[0.1016006434],"iteration":363,"passed_time":8.863945404,"remaining_time":15.48755296},
{"learn":[0.1015209246],"iteration":364,"passed_time":8.888628404,"remaining_time":15.46377818},
{"learn":[0.1014319777],"iteration":365,"passed_time":8.916363569,"remaining_time":15.44528553},
{"learn":[0.1013042488],"iteration":366,"passed_time":8.941055346,"remaining_time":15.42149328},
{"learn":[0.1010748821],"iteration":367,"passed_time":8.967628475,"remaining_time":15.40092716},
{"learn":[0.1009230951],"iteration":368,"passed_time":8.992944914,"remaining_time":15.37817951},
{"learn":[0.1008223476],"iteration":369,"passed_time":9.018911903,"remaining_time":15.35652567},
{"learn":[0.1007396006],"iteration":370,"passed_time":9.044569503,"remaining_time":15.33432404},
{"learn":[0.100629179],"iteration":371,"passed_time":9.070828407,"remaining_time":15.31311892},
{"learn":[0.1005546664],"iteration":372,"passed_time":9.099954477,"remaining_time":15.29670632},
{"learn":[0.1004552651],"iteration":373,"passed_time":9.125944556,"remaining_time":15.27497672},
{"learn":[0.1002959106],"iteration":374,"passed_time":9.153565542,"remaining_time":15.25594257},
{"learn":[0.1000713394],"iteration":375,"passed_time":9.179702388,"remaining_time":15.23439971},
{"learn":[0.0999669601],"iteration":376,"passed_time":9.205385564,"remaining_time":15.21208278},
{"learn":[0.09986205695],"iteration":377,"passed_time":9.232568264,"remaining_time":15.1922155},
{"learn":[0.09971915644],"iteration":378,"passed_time":9.259152311,"remaining_time":15.17132872},
{"learn":[0.09958166991],"iteration":379,"passed_time":9.285976261,"remaining_time":15.15080337},
{"learn":[0.09949847145],"iteration":380,"passed_time":9.313601293,"remaining_time":15.13154646},
{"learn":[0.09942282758],"iteration":381,"passed_time":9.337546455,"remaining_time":15.10629243},
{"learn":[0.09934233596],"iteration":382,"passed_time":9.361734455,"remaining_time":15.08143645},
{"learn":[0.09929735568],"iteration":383,"passed_time":9.390005831,"remaining_time":15.06313435},
{"learn":[0.09920682749],"iteration":384,"passed_time":9.415607213,"remaining_time":15.04051542},
{"learn":[0.09910398893],"iteration":385,"passed_time":9.440700137,"remaining_time":15.01707224},
{"learn":[0.09902616051],"iteration":386,"passed_time":9.464297671,"remaining_time":14.99125187},
{"learn":[0.09890615942],"iteration":387,"passed_time":9.491958637,"remaining_time":14.97185228},
{"learn":[0.09878054012],"iteration":388,"passed_time":9.517349371,"remaining_time":14.94884438},
{"learn":[0.0986645574],"iteration":389,"passed_time":9.542535484,"remaining_time":14.92550422},
{"learn":[0.09861191719],"iteration":390,"passed_time":9.566790936,"remaining_time":14.90070506},
{"learn":[0.09850516985],"iteration":391,"passed_time":9.591760036,"remaining_time":14.87701557},
{"learn":[0.09841983148],"iteration":392,"passed_time":9.617975567,"remaining_time":14.85524471},
{"learn":[0.09834439233],"iteration":393,"passed_time":9.641551067,"remaining_time":14.82939073},
{"learn":[0.09827076578],"iteration":394,"passed_time":9.665520567,"remaining_time":14.80415175},
{"learn":[0.09822723567],"iteration":395,"passed_time":9.688819628,"remaining_time":14.77789661},
{"learn":[0.0981354628],"iteration":396,"passed_time":9.714245711,"remaining_time":14.75488706},
{"learn":[0.09804066155],"iteration":397,"passed_time":9.742206916,"remaining_time":14.73569991},
{"learn":[0.09796456861],"iteration":398,"passed_time":9.769003254,"remaining_time":14.71471417},
{"learn":[0.09786553778],"iteration":399,"passed_time":9.79243501,"remaining_time":14.68865251},
{"learn":[0.09775149792],"iteration":400,"passed_time":9.815482581,"remaining_time":14.66203009},
{"learn":[0.09756062178],"iteration":401,"passed_time":9.840924237,"remaining_time":14.6389868},
{"learn":[0.09746191282],"iteration":402,"passed_time":9.867005163,"remaining_time":14.61687862},
{"learn":[0.09738877459],"iteration":403,"passed_time":9.89151921,"remaining_time":14.59243923},
{"learn":[0.09732348479],"iteration":404,"passed_time":9.91646352,"remaining_time":14.56863159},
{"learn":[0.09723921872],"iteration":405,"passed_time":9.940895642,"remaining_time":14.54406899},
{"learn":[0.09716242761],"iteration":406,"passed_time":9.965949869,"remaining_time":14.52041345},
{"learn":[0.09708495729],"iteration":407,"passed_time":9.99065354,"remaining_time":14.49624239},
{"learn":[0.09698218778],"iteration":408,"passed_time":10.01387937,"remaining_time":14.46993328},
{"learn":[0.0969086881],"iteration":409,"passed_time":10.03744179,"remaining_time":14.44412356},
{"learn":[0.09678763459],"iteration":410,"passed_time":10.06189506,"remaining_time":14.41960143},
{"learn":[0.0966779398],"iteration":411,"passed_time":10.08654394,"remaining_time":14.39535883},
{"learn":[0.09657046017],"iteration":412,"passed_time":10.1124999,"remaining_time":14.37297201},
{"learn":[0.09641706767],"iteration":413,"passed_time":10.13913476,"remaining_time":14.35152891},
{"learn":[0.09630477213],"iteration":414,"passed_time":10.16481693,"remaining_time":14.32871784},
{"learn":[0.09624372991],"iteration":415,"passed_time":10.18891613,"remaining_time":14.30367073},
{"learn":[0.09616598253],"iteration":416,"passed_time":10.21313501,"remaining_time":14.27879547},
{"learn":[0.09610563518],"iteration":417,"passed_time":10.23624732,"remaining_time":14.25238263},
{"learn":[0.09604434889],"iteration":418,"passed_time":10.25977672,"remaining_time":14.2265639},
{"learn":[0.09597693217],"iteration":419,"passed_time":10.28296941,"remaining_time":14.20029109},
{"learn":[0.09586011556],"iteration":420,"passed_time":10.30830405,"remaining_time":14.17697873},
{"learn":[0.09581812937],"iteration":421,"passed_time":10.33031795,"remaining_time":14.14910847},
{"learn":[0.09569205177],"iteration":422,"passed_time":10.35627335,"remaining_time":14.12664237},
{"learn":[0.09560487295],"iteration":423,"passed_time":10.38120521,"remaining_time":14.10276934},
{"learn":[0.0954896943],"iteration":424,"passed_time":10.4056765,"remaining_time":14.07826821},
{"learn":[0.09542216596],"iteration":425,"passed_time":10.4288386,"remaining_time":14.05200318},
{"learn":[0.09530644509],"iteration":426,"passed_time":10.4527791,"remaining_time":14.02679725},
{"learn":[0.0952241585],"iteration":427,"passed_time":10.47803824,"remaining_time":14.00335952},
{"learn":[0.09512998208],"iteration":428,"passed_time":10.50179946,"remaining_time":13.97791956},
{"learn":[0.09502620976],"iteration":429,"passed_time":10.52410691,"remaining_time":13.95056032},
{"learn":[0.09496794428],"iteration":430,"passed_time":10.5488937,"remaining_time":13.92649771},
{"learn":[0.09484522992],"iteration":431,"passed_time":10.57303107,"remaining_time":13.90157789},
{"learn":[0.09477044891],"iteration":432,"passed_time":10.59598482,"remaining_time":13.87511176},
{"learn":[0.09466724658],"iteration":433,"passed_time":10.61961055,"remaining_time":13.84953818},
{"learn":[0.09449145193],"iteration":434,"passed_time":10.6438257,"remaining_time":13.82473913},
{"learn":[0.09440802501],"iteration":435,"passed_time":10.66919311,"remaining_time":13.80143328},
{"learn":[0.09429943465],"iteration":436,"passed_time":10.69474865,"remaining_time":13.77836039},
{"learn":[0.09422459603],"iteration":437,"passed_time":10.71760428,"remaining_time":13.75181188},
{"learn":[0.09412776436],"iteration":438,"passed_time":10.74258574,"remaining_time":13.72799681},
{"learn":[0.09400669854],"iteration":439,"passed_time":10.76849715,"remaining_time":13.70536001},
{"learn":[0.09396042158],"iteration":440,"passed_time":10.79061556,"remaining_time":13.67790044},
{"learn":[0.09390497037],"iteration":441,"passed_time":10.81508888,"remaining_time":13.65343799},
{"learn":[0.09383416767],"iteration":442,"passed_time":10.83898021,"remaining_time":13.62824374},
{"learn":[0.09375324222],"iteration":443,"passed_time":10.86305781,"remaining_time":13.6032886},
{"learn":[0.09365880686],"iteration":444,"passed_time":10.88676268,"remaining_time":13.57787256},
{"learn":[0.09356876743],"iteration":445,"passed_time":10.91278138,"remaining_time":13.5553383},
{"learn":[0.09344086428],"iteration":446,"passed_time":10.93812591,"remaining_time":13.53195442},
{"learn":[0.09334944886],"iteration":447,"passed_time":10.96233839,"remaining_time":13.50716695},
{"learn":[0.093245107],"iteration":448,"passed_time":10.98540058,"remaining_time":13.48097042},
{"learn":[0.09318982218],"iteration":449,"passed_time":11.00785052,"remaining_time":13.45403952},
{"learn":[0.093109877],"iteration":450,"passed_time":11.03117948,"remaining_time":13.42819852},
{"learn":[0.09300588087],"iteration":451,"passed_time":11.0542993,"remaining_time":13.40211508},
{"learn":[0.09290354169],"iteration":452,"passed_time":11.07865161,"remaining_time":13.37753296},
{"learn":[0.09284818371],"iteration":453,"passed_time":11.10347347,"remaining_time":13.35351655},
{"learn":[0.0927718274],"iteration":454,"passed_time":11.12780484,"remaining_time":13.32890909},
{"learn":[0.09268972993],"iteration":455,"passed_time":11.15194284,"remaining_time":13.30407216},
{"learn":[0.09259786601],"iteration":456,"passed_time":11.17639753,"remaining_time":13.27961457},
{"learn":[0.09252330348],"iteration":457,"passed_time":11.20121694,"remaining_time":13.25558861},
{"learn":[0.09245083783],"iteration":458,"passed_time":11.2239972,"remaining_time":13.22915575},
{"learn":[0.09228468345],"iteration":459,"passed_time":11.24600333,"remaining_time":13.20183},
{"learn":[0.09216009485],"iteration":460,"passed_time":11.27008089,"remaining_time":13.17694924},
{"learn":[0.09207610312],"iteration":461,"passed_time":11.29449995,"remaining_time":13.15246964},
{"learn":[0.09201473641],"iteration":462,"passed_time":11.3185377,"remaining_time":13.12754804},
{"learn":[0.09194223289],"iteration":463,"passed_time":11.34365366,"remaining_time":13.10387578},
{"learn":[0.09186706361],"iteration":464,"passed_time":11.36731721,"remaining_time":13.07852625},
{"learn":[0.09177958914],"iteration":465,"passed_time":11.39203731,"remaining_time":13.05439468},
{"learn":[0.09162638024],"iteration":466,"passed_time":11.41744473,"remaining_time":13.03104505},
{"learn":[0.09156070947],"iteration":467,"passed_time":11.44185461,"remaining_time":13.00655267},
{"learn":[0.09148276866],"iteration":468,"passed_time":11.46615352,"remaining_time":12.98193501},
{"learn":[0.09140468241],"iteration":469,"passed_time":11.49141163,"remaining_time":12.95840035},
{"learn":[0.09131435867],"iteration":470,"passed_time":11.51620851,"remaining_time":12.93434034},
{"learn":[0.09125441161],"iteration":471,"passed_time":11.54218105,"remaining_time":12.91159236},
{"learn":[0.09112936829],"iteration":472,"passed_time":11.56692841,"remaining_time":12.88746569},
{"learn":[0.09104369897],"iteration":473,"passed_time":11.59251119,"remaining_time":12.86426347},
{"learn":[0.0909994341],"iteration":474,"passed_time":11.61800667,"remaining_time":12.84095474},
{"learn":[0.09090293751],"iteration":475,"passed_time":11.64233122,"remaining_time":12.81634782},
{"learn":[0.09074837939],"iteration":476,"passed_time":11.66760549,"remaining_time":12.79278338},
{"learn":[0.09064386179],"iteration":477,"passed_time":11.69328824,"remaining_time":12.76965787},
{"learn":[0.09058262766],"iteration":478,"passed_time":11.71769967,"remaining_time":12.74513889},
{"learn":[0.09049021616],"iteration":479,"passed_time":11.74128242,"remaining_time":12.71972262},
{"learn":[0.09042073453],"iteration":480,"passed_time":11.76899503,"remaining_time":12.69877011},
{"learn":[0.09029307479],"iteration":481,"passed_time":11.79408127,"remaining_time":12.67496701},
{"learn":[0.09019487355],"iteration":482,"passed_time":11.81765594,"remaining_time":12.64954063},
{"learn":[0.09012542503],"iteration":483,"passed_time":11.84031385,"remaining_time":12.62314451},
{"learn":[0.09003663844],"iteration":484,"passed_time":11.86520915,"remaining_time":12.59913961},
{"learn":[0.08994420784],"iteration":485,"passed_time":11.89073812,"remaining_time":12.57580123},
{"learn":[0.08989559115],"iteration":486,"passed_time":11.91512549,"remaining_time":12.55125129},
{"learn":[0.0898031329],"iteration":487,"passed_time":11.9392043,"remaining_time":12.52637828},
{"learn":[0.08972283549],"iteration":488,"passed_time":11.96159325,"remaining_time":12.49974264},
{"learn":[0.08963339896],"iteration":489,"passed_time":11.98561621,"remaining_time":12.47482504},
{"learn":[0.08955047234],"iteration":490,"passed_time":12.00893705,"remaining_time":12.44918321},
{"learn":[0.08948116225],"iteration":491,"passed_time":12.03339515,"remaining_time":12.42472508},
{"learn":[0.08939345226],"iteration":492,"passed_time":12.05656155,"remaining_time":12.39893855},
{"learn":[0.08930816538],"iteration":493,"passed_time":12.08158974,"remaining_time":12.37506965},
{"learn":[0.08925317676],"iteration":494,"passed_time":12.10448326,"remaining_time":12.34901828},
{"learn":[0.0891636494],"iteration":495,"passed_time":12.12734145,"remaining_time":12.32294373},
{"learn":[0.08907370112],"iteration":496,"passed_time":12.15331253,"remaining_time":12.3000326},
{"learn":[0.08896830578],"iteration":497,"passed_time":12.1772427,"remaining_time":12.27505188},
{"learn":[0.08886324553],"iteration":498,"passed_time":12.20030871,"remaining_time":12.24920775},
{"learn":[0.08874256409],"iteration":499,"passed_time":12.22434196,"remaining_time":12.22434196},
{"learn":[0.08870151617],"iteration":500,"passed_time":12.24964134,"remaining_time":12.20074057},
{"learn":[0.08861269752],"iteration":501,"passed_time":12.27486436,"remaining_time":12.17705667},
{"learn":[0.08850343037],"iteration":502,"passed_time":12.29978028,"remaining_time":12.15306322},
{"learn":[0.08845188254],"iteration":503,"passed_time":12.32476378,"remaining_time":12.12913261},
{"learn":[0.08833326882],"iteration":504,"passed_time":12.34882502,"remaining_time":12.10429383},
{"learn":[0.08819858824],"iteration":505,"passed_time":12.37184928,"remaining_time":12.07844574},
{"learn":[0.08809211915],"iteration":506,"passed_time":12.39715479,"remaining_time":12.05482704},
{"learn":[0.08801927383],"iteration":507,"passed_time":12.42112149,"remaining_time":12.02990506},
{"learn":[0.08794520253],"iteration":508,"passed_time":12.44651345,"remaining_time":12.00636169},
{"learn":[0.08787810504],"iteration":509,"passed_time":12.47061785,"remaining_time":11.98157401},
{"learn":[0.08773178722],"iteration":510,"passed_time":12.49646684,"remaining_time":11.95845848},
{"learn":[0.08766406174],"iteration":511,"passed_time":12.52144132,"remaining_time":11.93449876},
{"learn":[0.08757359568],"iteration":512,"passed_time":12.54746497,"remaining_time":11.91153107},
{"learn":[0.08749075742],"iteration":513,"passed_time":12.57261419,"remaining_time":11.8877247},
{"learn":[0.08742201435],"iteration":514,"passed_time":12.59661073,"remaining_time":11.86282759},
{"learn":[0.08732868957],"iteration":515,"passed_time":12.6204596,"remaining_time":11.83779544},
{"learn":[0.08722859126],"iteration":516,"passed_time":12.64674091,"remaining_time":11.81504034},
{"learn":[0.0871244822],"iteration":517,"passed_time":12.67355015,"remaining_time":11.79276288},
{"learn":[0.08705364083],"iteration":518,"passed_time":12.69818108,"remaining_time":11.76844913},
{"learn":[0.08698788665],"iteration":519,"passed_time":12.72135116,"remaining_time":11.74278569},
{"learn":[0.08693790211],"iteration":520,"passed_time":12.74476311,"remaining_time":11.71735418},
{"learn":[0.08687464989],"iteration":521,"passed_time":12.76767925,"remaining_time":11.6914764},
{"learn":[0.0867888332],"iteration":522,"passed_time":12.79244508,"remaining_time":11.66729695},
{"learn":[0.08669832306],"iteration":523,"passed_time":12.81681014,"remaining_time":11.6427512},
{"learn":[0.08664482417],"iteration":524,"passed_time":12.84092192,"remaining_time":11.61797698},
{"learn":[0.086572263],"iteration":525,"passed_time":12.86445213,"remaining_time":11.5926812},
{"learn":[0.08653413199],"iteration":526,"passed_time":12.88632989,"remaining_time":11.56590899},
{"learn":[0.08642561531],"iteration":527,"passed_time":12.9091335,"remaining_time":11.53998297},
{"learn":[0.08635928118],"iteration":528,"passed_time":12.93080036,"remaining_time":11.51305666},
{"learn":[0.08631121737],"iteration":529,"passed_time":12.95310419,"remaining_time":11.48671503},
{"learn":[0.08624119957],"iteration":530,"passed_time":12.97713519,"remaining_time":11.46191413},
{"learn":[0.08618878825],"iteration":531,"passed_time":13.00036411,"remaining_time":11.43641054},
{"learn":[0.0861232739],"iteration":532,"passed_time":13.02199784,"remaining_time":11.4095178},
{"learn":[0.0860435815],"iteration":533,"passed_time":13.04828557,"remaining_time":11.38670613},
{"learn":[0.08593373416],"iteration":534,"passed_time":13.07400806,"remaining_time":11.36339018},
{"learn":[0.08586016746],"iteration":535,"passed_time":13.09757742,"remaining_time":11.33820134},
{"learn":[0.08578493723],"iteration":536,"passed_time":13.1212217,"remaining_time":11.31308314},
{"learn":[0.08571706182],"iteration":537,"passed_time":13.14608934,"remaining_time":11.28902096},
{"learn":[0.08563585216],"iteration":538,"passed_time":13.1691681,"remaining_time":11.26342578},
{"learn":[0.08552251787],"iteration":539,"passed_time":13.19265046,"remaining_time":11.23818372},
{"learn":[0.08539065462],"iteration":540,"passed_time":13.21852393,"remaining_time":11.21497687},
{"learn":[0.08530621915],"iteration":541,"passed_time":13.24132267,"remaining_time":11.18916196},
{"learn":[0.08524674905],"iteration":542,"passed_time":13.26432408,"remaining_time":11.16352874},
{"learn":[0.08515625138],"iteration":543,"passed_time":13.28681739,"remaining_time":11.13747928},
{"learn":[0.08505239422],"iteration":544,"passed_time":13.31238112,"remaining_time":11.11400626},
{"learn":[0.08499348983],"iteration":545,"passed_time":13.33606845,"remaining_time":11.08896534},
{"learn":[0.08488811661],"iteration":546,"passed_time":13.35992605,"remaining_time":11.06407039},
{"learn":[0.084815647],"iteration":547,"passed_time":13.38423643,"remaining_time":11.03955267},
{"learn":[0.08476357553],"iteration":548,"passed_time":13.40811936,"remaining_time":11.01468457},
{"learn":[0.08470541279],"iteration":549,"passed_time":13.43226306,"remaining_time":10.99003341},
{"learn":[0.08457936628],"iteration":550,"passed_time":13.45646579,"remaining_time":10.96543219},
{"learn":[0.08448413977],"iteration":551,"passed_time":13.48121043,"remaining_time":10.94127223},
{"learn":[0.08436492949],"iteration":552,"passed_time":13.50661794,"remaining_time":10.91764597},
{"learn":[0.08427906875],"iteration":553,"passed_time":13.53174709,"remaining_time":10.89378918},
{"learn":[0.08421940234],"iteration":554,"passed_time":13.55647199,"remaining_time":10.86960366},
{"learn":[0.08412475847],"iteration":555,"passed_time":13.58088757,"remaining_time":10.84516921},
{"learn":[0.08407092986],"iteration":556,"passed_time":13.60677248,"remaining_time":10.82190343},
{"learn":[0.08399025781],"iteration":557,"passed_time":13.6318709,"remaining_time":10.79800527},
{"learn":[0.08388989997],"iteration":558,"passed_time":13.65585397,"remaining_time":10.7732229},
{"learn":[0.08379096643],"iteration":559,"passed_time":13.68086103,"remaining_time":10.74924796},
{"learn":[0.08368838183],"iteration":560,"passed_time":13.70532649,"remaining_time":10.72484551},
{"learn":[0.08361953931],"iteration":561,"passed_time":13.73055139,"remaining_time":10.70103471},
{"learn":[0.08358210379],"iteration":562,"passed_time":13.75389644,"remaining_time":10.67575976},
{"learn":[0.08352602517],"iteration":563,"passed_time":13.77846485,"remaining_time":10.65143736},
{"learn":[0.08344521148],"iteration":564,"passed_time":13.80290891,"remaining_time":10.62701837},
{"learn":[0.08335145911],"iteration":565,"passed_time":13.8272,"remaining_time":10.60248198},
{"learn":[0.08327797292],"iteration":566,"passed_time":13.85109418,"remaining_time":10.57764335},
{"learn":[0.08318934447],"iteration":567,"passed_time":13.87541695,"remaining_time":10.55313402},
{"learn":[0.08311115208],"iteration":568,"passed_time":13.90197773,"remaining_time":10.53032056},
{"learn":[0.08302920663],"iteration":569,"passed_time":13.92626235,"remaining_time":10.50577686},
{"learn":[0.08292166664],"iteration":570,"passed_time":13.95181421,"remaining_time":10.48218616},
{"learn":[0.08280542374],"iteration":571,"passed_time":13.97713238,"remaining_time":10.45841374},
{"learn":[0.08273920471],"iteration":572,"passed_time":14.00164433,"remaining_time":10.43403513},
{"learn":[0.08267208363],"iteration":573,"passed_time":14.0271485,"remaining_time":10.41039244},
{"learn":[0.08257289432],"iteration":574,"passed_time":14.05113011,"remaining_time":10.38561791},
{"learn":[0.08247127941],"iteration":575,"passed_time":14.07659181,"remaining_time":10.36193564},
{"learn":[0.08243097489],"iteration":576,"passed_time":14.10277751,"remaining_time":10.33877796},
{"learn":[0.08233483943],"iteration":577,"passed_time":14.12807016,"remaining_time":10.3149578},
{"learn":[0.08224712269],"iteration":578,"passed_time":14.15235571,"remaining_time":10.29040026},
{"learn":[0.08216898281],"iteration":579,"passed_time":14.17793347,"remaining_time":10.26677941},
{"learn":[0.08211360947],"iteration":580,"passed_time":14.20475955,"remaining_time":10.24405207},
{"learn":[0.08196977158],"iteration":581,"passed_time":14.22917855,"remaining_time":10.21958184},
{"learn":[0.0819081041],"iteration":582,"passed_time":14.25157294,"remaining_time":10.19366367},
{"learn":[0.08185286105],"iteration":583,"passed_time":14.27470077,"remaining_time":10.16828},
{"learn":[0.08176654927],"iteration":584,"passed_time":14.29914406,"remaining_time":10.14383724},
{"learn":[0.08169228326],"iteration":585,"passed_time":14.321941,"remaining_time":10.11823136},
{"learn":[0.08160280541],"iteration":586,"passed_time":14.34653135,"remaining_time":10.09389685},
{"learn":[0.08153024241],"iteration":587,"passed_time":14.37028446,"remaining_time":10.06897483},
{"learn":[0.08148721098],"iteration":588,"passed_time":14.39464466,"remaining_time":10.0444804},
{"learn":[0.08142300304],"iteration":589,"passed_time":14.4171711,"remaining_time":10.01871212},
{"learn":[0.08135740312],"iteration":590,"passed_time":14.44209478,"remaining_time":9.994613817},
{"learn":[0.08127567914],"iteration":591,"passed_time":14.46690921,"remaining_time":9.970437432},
{"learn":[0.08121563068],"iteration":592,"passed_time":14.49079235,"remaining_time":9.945619709},
{"learn":[0.08114848788],"iteration":593,"passed_time":14.51474236,"remaining_time":9.920850836},
{"learn":[0.08106994994],"iteration":594,"passed_time":14.53897942,"remaining_time":9.896280107},
{"learn":[0.08099131988],"iteration":595,"passed_time":14.56124205,"remaining_time":9.870372128},
{"learn":[0.08090256291],"iteration":596,"passed_time":14.58493087,"remaining_time":9.845439094},
{"learn":[0.08081519392],"iteration":597,"passed_time":14.61096985,"remaining_time":9.822090098},
{"learn":[0.08070875246],"iteration":598,"passed_time":14.63369664,"remaining_time":9.796514779},
{"learn":[0.08064849834],"iteration":599,"passed_time":14.65781433,"remaining_time":9.771876218},
{"learn":[0.08054865452],"iteration":600,"passed_time":14.68295487,"remaining_time":9.747918455},
{"learn":[0.08049438493],"iteration":601,"passed_time":14.70742509,"remaining_time":9.723513597},
{"learn":[0.08045977684],"iteration":602,"passed_time":14.7289307,"remaining_time":9.697156695},
{"learn":[0.08039915313],"iteration":603,"passed_time":14.7539145,"remaining_time":9.673096261},
{"learn":[0.08031616606],"iteration":604,"passed_time":14.77780831,"remaining_time":9.648321127},
{"learn":[0.0801859544],"iteration":605,"passed_time":14.80374114,"remaining_time":9.624874599},
{"learn":[0.08013284084],"iteration":606,"passed_time":14.8281115,"remaining_time":9.600408268},
{"learn":[0.08009773692],"iteration":607,"passed_time":14.85044628,"remaining_time":9.574629836},
{"learn":[0.08000842234],"iteration":608,"passed_time":14.87695759,"remaining_time":9.551544198},
{"learn":[0.07993168662],"iteration":609,"passed_time":14.90251847,"remaining_time":9.527839677},
{"learn":[0.07986444766],"iteration":610,"passed_time":14.92744554,"remaining_time":9.503725556},
{"learn":[0.07981310865],"iteration":611,"passed_time":14.95213413,"remaining_time":9.479457583},
{"learn":[0.07973624934],"iteration":612,"passed_time":14.97726099,"remaining_time":9.45546493},
{"learn":[0.079676773],"iteration":613,"passed_time":15.00149683,"remaining_time":9.430908433},
{"learn":[0.07959626318],"iteration":614,"passed_time":15.02728727,"remaining_time":9.407326177},
{"learn":[0.07955915528],"iteration":615,"passed_time":15.05088706,"remaining_time":9.382371152},
{"learn":[0.07949792863],"iteration":616,"passed_time":15.07546598,"remaining_time":9.358028317},
{"learn":[0.07940373589],"iteration":617,"passed_time":15.09959316,"remaining_time":9.333405482},
{"learn":[0.07931898124],"iteration":618,"passed_time":15.12260501,"remaining_time":9.308097753},
{"learn":[0.0792971453],"iteration":619,"passed_time":15.14571228,"remaining_time":9.282855912},
{"learn":[0.07921495841],"iteration":620,"passed_time":15.16929796,"remaining_time":9.257912926},
{"learn":[0.07914718588],"iteration":621,"passed_time":15.19264869,"remaining_time":9.232831519},
{"learn":[0.07911898294],"iteration":622,"passed_time":15.21456132,"remaining_time":9.206885424},
{"learn":[0.07905811251],"iteration":623,"passed_time":15.23947547,"remaining_time":9.182760862},
{"learn":[0.07898008582],"iteration":624,"passed_time":15.26449878,"remaining_time":9.158699268},
{"learn":[0.07889555472],"iteration":625,"passed_time":15.2887106,"remaining_time":9.134149783},
{"learn":[0.07882413582],"iteration":626,"passed_time":15.31330931,"remaining_time":9.109831536},
{"learn":[0.07874886173],"iteration":627,"passed_time":15.33865058,"remaining_time":9.085952256},
{"learn":[0.07868363391],"iteration":628,"passed_time":15.3630494,"remaining_time":9.061512444},
{"learn":[0.07861832329],"iteration":629,"passed_time":15.38839066,"remaining_time":9.037626263},
{"learn":[0.07855600173],"iteration":630,"passed_time":15.41360072,"remaining_time":9.013658742},
{"learn":[0.07847816405],"iteration":631,"passed_time":15.43915424,"remaining_time":8.989887281},
{"learn":[0.07840386699],"iteration":632,"passed_time":15.46287364,"remaining_time":8.965046804},
{"learn":[0.07836095943],"iteration":633,"passed_time":15.4866384,"remaining_time":8.940236049},
{"learn":[0.07829038448],"iteration":634,"passed_time":15.51010391,"remaining_time":8.915256575},
{"learn":[0.07822342457],"iteration":635,"passed_time":15.53249321,"remaining_time":8.889665928},
{"learn":[0.07813396918],"iteration":636,"passed_time":15.55692928,"remaining_time":8.865251691},
{"learn":[0.07807702884],"iteration":637,"passed_time":15.58263483,"remaining_time":8.841557691},
{"learn":[0.07799387747],"iteration":638,"passed_time":15.60733693,"remaining_time":8.817290504},
{"learn":[0.07793571062],"iteration":639,"passed_time":15.63150685,"remaining_time":8.792722604},
{"learn":[0.07790519382],"iteration":640,"passed_time":15.65564567,"remaining_time":8.768138527},
{"learn":[0.07785826722],"iteration":641,"passed_time":15.68036467,"remaining_time":8.743879363},
{"learn":[0.0777986225],"iteration":642,"passed_time":15.70576212,"remaining_time":8.719995452},
{"learn":[0.0777493085],"iteration":643,"passed_time":15.72982438,"remaining_time":8.695368755},
{"learn":[0.07764239975],"iteration":644,"passed_time":15.75622924,"remaining_time":8.67203315},
{"learn":[0.07758439327],"iteration":645,"passed_time":15.78090911,"remaining_time":8.647742762},
{"learn":[0.07752259798],"iteration":646,"passed_time":15.80313127,"remaining_time":8.622110261},
{"learn":[0.07747770583],"iteration":647,"passed_time":15.82473528,"remaining_time":8.596152499},
{"learn":[0.07740166594],"iteration":648,"passed_time":15.84903141,"remaining_time":8.571664137},
{"learn":[0.07731062449],"iteration":649,"passed_time":15.87154326,"remaining_time":8.546215603},
{"learn":[0.07721220775],"iteration":650,"passed_time":15.8984593,"remaining_time":8.523137168},
{"learn":[0.07714360338],"iteration":651,"passed_time":15.92450428,"remaining_time":8.49958204},
{"learn":[0.07707235523],"iteration":652,"passed_time":15.95019776,"remaining_time":8.4758325},
{"learn":[0.07700094174],"iteration":653,"passed_time":15.97569614,"remaining_time":8.451973801},
{"learn":[0.07695211477],"iteration":654,"passed_time":15.99919945,"remaining_time":8.427059253},
{"learn":[0.07687586768],"iteration":655,"passed_time":16.0241567,"remaining_time":8.402911442},
{"learn":[0.07683749663],"iteration":656,"passed_time":16.04746818,"remaining_time":8.377901957},
{"learn":[0.07678287597],"iteration":657,"passed_time":16.07219243,"remaining_time":8.353631931},
{"learn":[0.07670082412],"iteration":658,"passed_time":16.09503574,"remaining_time":8.328387232},
{"learn":[0.07664350608],"iteration":659,"passed_time":16.11929341,"remaining_time":8.303878426},
{"learn":[0.07658404128],"iteration":660,"passed_time":16.14462903,"remaining_time":8.279923209},
{"learn":[0.07651430142],"iteration":661,"passed_time":16.16857825,"remaining_time":8.255255966},
{"learn":[0.07646605703],"iteration":662,"passed_time":16.19199879,"remaining_time":8.230322162},
{"learn":[0.07639511874],"iteration":663,"passed_time":16.21769453,"remaining_time":8.206544218},
{"learn":[0.07636076113],"iteration":664,"passed_time":16.24354955,"remaining_time":8.182840752},
{"learn":[0.07631535734],"iteration":665,"passed_time":16.26670316,"remaining_time":8.157776061},
{"learn":[0.07624125752],"iteration":666,"passed_time":16.29116184,"remaining_time":8.133368653},
{"learn":[0.07613260799],"iteration":667,"passed_time":16.31785508,"remaining_time":8.110071686},
{"learn":[0.07606816913],"iteration":668,"passed_time":16.34396966,"remaining_time":8.086478262},
{"learn":[0.07602081086],"iteration":669,"passed_time":16.36907584,"remaining_time":8.062380637},
{"learn":[0.07594015853],"iteration":670,"passed_time":16.39225535,"remaining_time":8.037335335},
{"learn":[0.07588465417],"iteration":671,"passed_time":16.41713078,"remaining_time":8.013123358},
{"learn":[0.07580504216],"iteration":672,"passed_time":16.44327563,"remaining_time":7.9895262},
{"learn":[0.07571678539],"iteration":673,"passed_time":16.46865963,"remaining_time":7.965553471},
{"learn":[0.07564901919],"iteration":674,"passed_time":16.49507492,"remaining_time":7.942073108},
{"learn":[0.07560138953],"iteration":675,"passed_time":16.52094675,"remaining_time":7.918323589},
{"learn":[0.07555127709],"iteration":676,"passed_time":16.54460019,"remaining_time":7.893509398},
{"learn":[0.07547560832],"iteration":677,"passed_time":16.57067325,"remaining_time":7.869847767},
{"learn":[0.07540172825],"iteration":678,"passed_time":16.59538568,"remaining_time":7.845535795},
{"learn":[0.07535987416],"iteration":679,"passed_time":16.621348,"remaining_time":7.821810823},
{"learn":[0.07531206858],"iteration":680,"passed_time":16.64426559,"remaining_time":7.796653044},
{"learn":[0.07527168005],"iteration":681,"passed_time":16.66990764,"remaining_time":7.772772185},
{"learn":[0.0751778062],"iteration":682,"passed_time":16.69603023,"remaining_time":7.749109198},
{"learn":[0.07510159666],"iteration":683,"passed_time":16.72257486,"remaining_time":7.725633999},
{"learn":[0.07505892453],"iteration":684,"passed_time":16.74549595,"remaining_time":7.700483539},
{"learn":[0.07497111544],"iteration":685,"passed_time":16.76831659,"remaining_time":7.675293599},
{"learn":[0.07490310206],"iteration":686,"passed_time":16.79297162,"remaining_time":7.650946311},
{"learn":[0.07482866163],"iteration":687,"passed_time":16.81647567,"remaining_time":7.626076177},
{"learn":[0.07478334899],"iteration":688,"passed_time":16.83997973,"remaining_time":7.601210009},
{"learn":[0.07473350699],"iteration":689,"passed_time":16.8630779,"remaining_time":7.576165433},
{"learn":[0.07463990079],"iteration":690,"passed_time":16.88796948,"remaining_time":7.551928465},
{"learn":[0.07459201734],"iteration":691,"passed_time":16.91129442,"remaining_time":7.526992316},
{"learn":[0.07450214954],"iteration":692,"passed_time":16.93631844,"remaining_time":7.502813509},
{"learn":[0.07446315551],"iteration":693,"passed_time":16.95934684,"remaining_time":7.477752352},
{"learn":[0.07437974716],"iteration":694,"passed_time":16.98501622,"remaining_time":7.45385604},
{"learn":[0.07432208822],"iteration":695,"passed_time":17.00818412,"remaining_time":7.428862031},
{"learn":[0.07425993658],"iteration":696,"passed_time":17.03406633,"remaining_time":7.405053225},
{"learn":[0.07422124719],"iteration":697,"passed_time":17.05635919,"remaining_time":7.379685493},
{"learn":[0.07410975668],"iteration":698,"passed_time":17.07997985,"remaining_time":7.354898335},
{"learn":[0.0740540698],"iteration":699,"passed_time":17.10372711,"remaining_time":7.330168762},
{"learn":[0.07400400019],"iteration":700,"passed_time":17.12824432,"remaining_time":7.305770401},
{"learn":[0.07395480772],"iteration":701,"passed_time":17.15335434,"remaining_time":7.281623352},
{"learn":[0.07386794723],"iteration":702,"passed_time":17.17870001,"remaining_time":7.257573119},
{"learn":[0.07378358907],"iteration":703,"passed_time":17.20519376,"remaining_time":7.234001922},
{"learn":[0.07372457541],"iteration":704,"passed_time":17.22916294,"remaining_time":7.209366053},
{"learn":[0.07363856825],"iteration":705,"passed_time":17.25343455,"remaining_time":7.184858013},
{"learn":[0.07357031716],"iteration":706,"passed_time":17.27841003,"remaining_time":7.160642345},
{"learn":[0.0735247075],"iteration":707,"passed_time":17.3030893,"remaining_time":7.136302367},
{"learn":[0.07346291948],"iteration":708,"passed_time":17.3291618,"remaining_time":7.112533262},
{"learn":[0.07340721161],"iteration":709,"passed_time":17.35242157,"remaining_time":7.08760881},
{"learn":[0.07336232522],"iteration":710,"passed_time":17.37579504,"remaining_time":7.062735256},
{"learn":[0.07330865473],"iteration":711,"passed_time":17.40040732,"remaining_time":7.038367007},
{"learn":[0.07324495153],"iteration":712,"passed_time":17.42458752,"remaining_time":7.01382415},
{"learn":[0.07317912732],"iteration":713,"passed_time":17.45004743,"remaining_time":6.989794909},
{"learn":[0.07310410338],"iteration":714,"passed_time":17.47659477,"remaining_time":6.96619512},
{"learn":[0.07304465002],"iteration":715,"passed_time":17.50071081,"remaining_time":6.941622722},
{"learn":[0.07300628645],"iteration":716,"passed_time":17.52507155,"remaining_time":6.917148185},
{"learn":[0.07292162688],"iteration":717,"passed_time":17.54777171,"remaining_time":6.892021759},
{"learn":[0.07287321079],"iteration":718,"passed_time":17.57004148,"remaining_time":6.866733875},
{"learn":[0.07282949902],"iteration":719,"passed_time":17.59232174,"remaining_time":6.841458454},
{"learn":[0.07277716409],"iteration":720,"passed_time":17.61542832,"remaining_time":6.816511098},
{"learn":[0.07271072979],"iteration":721,"passed_time":17.64060009,"remaining_time":6.792364025},
{"learn":[0.07264552191],"iteration":722,"passed_time":17.66526241,"remaining_time":6.768018931},
{"learn":[0.07260211983],"iteration":723,"passed_time":17.68871778,"remaining_time":6.743212857},
{"learn":[0.07254656422],"iteration":724,"passed_time":17.71212062,"remaining_time":6.718390581},
{"learn":[0.07246480971],"iteration":725,"passed_time":17.73520435,"remaining_time":6.693451778},
{"learn":[0.07243728426],"iteration":726,"passed_time":17.75904267,"remaining_time":6.668801443},
{"learn":[0.07237711042],"iteration":727,"passed_time":17.78165653,"remaining_time":6.643695848},
{"learn":[0.07233067676],"iteration":728,"passed_time":17.80644184,"remaining_time":6.619404304},
{"learn":[0.07225290022],"iteration":729,"passed_time":17.83167319,"remaining_time":6.595276384},
{"learn":[0.07220270216],"iteration":730,"passed_time":17.85551331,"remaining_time":6.570633491},
{"learn":[0.07206828366],"iteration":731,"passed_time":17.87751132,"remaining_time":6.545318353},
{"learn":[0.07200218082],"iteration":732,"passed_time":17.9042939,"remaining_time":6.521755077},
{"learn":[0.07196443582],"iteration":733,"passed_time":17.92760356,"remaining_time":6.496924451},
{"learn":[0.07186026238],"iteration":734,"passed_time":17.95112811,"remaining_time":6.472175442},
{"learn":[0.07181003448],"iteration":735,"passed_time":17.97564602,"remaining_time":6.447786071},
{"learn":[0.07174091619],"iteration":736,"passed_time":17.99835459,"remaining_time":6.422750687},
{"learn":[0.07167805881],"iteration":737,"passed_time":18.02136778,"remaining_time":6.397829753},
{"learn":[0.07161453619],"iteration":738,"passed_time":18.04506863,"remaining_time":6.373156849},
{"learn":[0.07153416186],"iteration":739,"passed_time":18.0711724,"remaining_time":6.349330843},
{"learn":[0.07150300621],"iteration":740,"passed_time":18.09405848,"remaining_time":6.324374016},
{"learn":[0.07144782923],"iteration":741,"passed_time":18.11861533,"remaining_time":6.300003713},
{"learn":[0.07137714643],"iteration":742,"passed_time":18.14489874,"remaining_time":6.276230115},
{"learn":[0.07132581555],"iteration":743,"passed_time":18.16810852,"remaining_time":6.25139218},
{"learn":[0.07127869346],"iteration":744,"passed_time":18.19191069,"remaining_time":6.226761376},
{"learn":[0.07117847259],"iteration":745,"passed_time":18.21500777,"remaining_time":6.201892726},
{"learn":[0.07114078806],"iteration":746,"passed_time":18.24027715,"remaining_time":6.177764551},
{"learn":[0.07107845842],"iteration":747,"passed_time":18.26515753,"remaining_time":6.15350227},
{"learn":[0.07102097512],"iteration":748,"passed_time":18.29127128,"remaining_time":6.129651658},
{"learn":[0.07094789323],"iteration":749,"passed_time":18.31473985,"remaining_time":6.104913283},
{"learn":[0.0708972503],"iteration":750,"passed_time":18.33975828,"remaining_time":6.080692161},
{"learn":[0.0708017184],"iteration":751,"passed_time":18.36469381,"remaining_time":6.056441575},
{"learn":[0.07075130512],"iteration":752,"passed_time":18.38864719,"remaining_time":6.031867006},
{"learn":[0.07071014432],"iteration":753,"passed_time":18.41367485,"remaining_time":6.007644581},
{"learn":[0.07066963421],"iteration":754,"passed_time":18.4408606,"remaining_time":5.984120327},
{"learn":[0.07062661889],"iteration":755,"passed_time":18.46728465,"remaining_time":5.960340547},
{"learn":[0.07059320534],"iteration":756,"passed_time":18.49247612,"remaining_time":5.936158119},
{"learn":[0.07055116214],"iteration":757,"passed_time":18.51830824,"remaining_time":5.912177563},
{"learn":[0.07052316471],"iteration":758,"passed_time":18.5440684,"remaining_time":5.88816928},
{"learn":[0.07048743044],"iteration":759,"passed_time":18.57004052,"remaining_time":5.864223323},
{"learn":[0.07042746261],"iteration":760,"passed_time":18.5954485,"remaining_time":5.840094865},
{"learn":[0.07039557251],"iteration":761,"passed_time":18.62155692,"remaining_time":5.816181821},
{"learn":[0.07034282705],"iteration":762,"passed_time":18.6490394,"remaining_time":5.792689828},
{"learn":[0.07026229799],"iteration":763,"passed_time":18.67372968,"remaining_time":5.768324876},
{"learn":[0.07020312325],"iteration":764,"passed_time":18.69737901,"remaining_time":5.743639303},
{"learn":[0.07017196123],"iteration":765,"passed_time":18.72158775,"remaining_time":5.719127327},
{"learn":[0.07008392643],"iteration":766,"passed_time":18.74700029,"remaining_time":5.694981835},
{"learn":[0.07002679426],"iteration":767,"passed_time":18.77279505,"remaining_time":5.670948506},
{"learn":[0.06995801665],"iteration":768,"passed_time":18.79693839,"remaining_time":5.646414522},
{"learn":[0.0698970476],"iteration":769,"passed_time":18.82085926,"remaining_time":5.621815103},
{"learn":[0.0698456492],"iteration":770,"passed_time":18.84830463,"remaining_time":5.598264281},
{"learn":[0.06977571873],"iteration":771,"passed_time":18.874609,"remaining_time":5.57436639},
{"learn":[0.06970404983],"iteration":772,"passed_time":18.90103241,"remaining_time":5.550497227},
{"learn":[0.06967193807],"iteration":773,"passed_time":18.92631011,"remaining_time":5.526286932},
{"learn":[0.06958103584],"iteration":774,"passed_time":18.95205788,"remaining_time":5.502210351},
{"learn":[0.06952780129],"iteration":775,"passed_time":18.97833064,"remaining_time":5.478281008},
{"learn":[0.06948487494],"iteration":776,"passed_time":19.00247482,"remaining_time":5.453734729},
{"learn":[0.06942404648],"iteration":777,"passed_time":19.02869023,"remaining_time":5.429780502},
{"learn":[0.0693526408],"iteration":778,"passed_time":19.05938271,"remaining_time":5.407090602},
{"learn":[0.06929580944],"iteration":779,"passed_time":19.08272053,"remaining_time":5.38230579},
{"learn":[0.06922807325],"iteration":780,"passed_time":19.10911569,"remaining_time":5.358381992},
{"learn":[0.06918044752],"iteration":781,"passed_time":19.13463293,"remaining_time":5.334207135},
{"learn":[0.06911862107],"iteration":782,"passed_time":19.15917728,"remaining_time":5.30975922},
{"learn":[0.06908356446],"iteration":783,"passed_time":19.18432643,"remaining_time":5.285477689},
{"learn":[0.06903493703],"iteration":784,"passed_time":19.20831296,"remaining_time":5.260875524},
{"learn":[0.06899182935],"iteration":785,"passed_time":19.23425473,"remaining_time":5.236807267},
{"learn":[0.06894613478],"iteration":786,"passed_time":19.26012118,"remaining_time":5.212713864},
{"learn":[0.06888077828],"iteration":787,"passed_time":19.28486292,"remaining_time":5.188313376},
{"learn":[0.06883596128],"iteration":788,"passed_time":19.3087696,"remaining_time":5.163688701},
{"learn":[0.06879575108],"iteration":789,"passed_time":19.33220142,"remaining_time":5.138939617},
{"learn":[0.06872553812],"iteration":790,"passed_time":19.35636309,"remaining_time":5.114386709},
{"learn":[0.06867933887],"iteration":791,"passed_time":19.38218086,"remaining_time":5.090269721},
{"learn":[0.06858899902],"iteration":792,"passed_time":19.40956703,"remaining_time":5.066557852},
{"learn":[0.06853493806],"iteration":793,"passed_time":19.4339238,"remaining_time":5.04205076},
{"learn":[0.06846368949],"iteration":794,"passed_time":19.4589521,"remaining_time":5.017717208},
{"learn":[0.06841700473],"iteration":795,"passed_time":19.48397565,"remaining_time":4.993380695},
{"learn":[0.06836062276],"iteration":796,"passed_time":19.5100653,"remaining_time":4.969313997},
{"learn":[0.0683160276],"iteration":797,"passed_time":19.53565948,"remaining_time":4.945116811},
{"learn":[0.06826237656],"iteration":798,"passed_time":19.55904269,"remaining_time":4.920359926},
{"learn":[0.06821190487],"iteration":799,"passed_time":19.58405934,"remaining_time":4.896014834},
{"learn":[0.06815708763],"iteration":800,"passed_time":19.60937885,"remaining_time":4.87174331},
{"learn":[0.068082065],"iteration":801,"passed_time":19.63463945,"remaining_time":4.847454628},
{"learn":[0.06800916912],"iteration":802,"passed_time":19.65865797,"remaining_time":4.822858805},
{"learn":[0.06795364442],"iteration":803,"passed_time":19.68235668,"remaining_time":4.798186455},
{"learn":[0.06788286761],"iteration":804,"passed_time":19.70862285,"remaining_time":4.774138455},
{"learn":[0.06782782505],"iteration":805,"passed_time":19.73409668,"remaining_time":4.749894238},
{"learn":[0.0677989683],"iteration":806,"passed_time":19.75942564,"remaining_time":4.725612327},
{"learn":[0.0677400391],"iteration":807,"passed_time":19.78393651,"remaining_time":4.701133428},
{"learn":[0.06769258897],"iteration":808,"passed_time":19.80793126,"remaining_time":4.676532597},
{"learn":[0.06764915066],"iteration":809,"passed_time":19.83334612,"remaining_time":4.652266374},
{"learn":[0.0675861042],"iteration":810,"passed_time":19.85992102,"remaining_time":4.62826766},
{"learn":[0.06753576946],"iteration":811,"passed_time":19.88569203,"remaining_time":4.604076479},
{"learn":[0.06747331131],"iteration":812,"passed_time":19.91113232,"remaining_time":4.579805342},
{"learn":[0.06739905356],"iteration":813,"passed_time":19.93963894,"remaining_time":4.556231993},
{"learn":[0.06737119289],"iteration":814,"passed_time":19.96333783,"remaining_time":4.531555213},
{"learn":[0.06732904655],"iteration":815,"passed_time":19.9891037,"remaining_time":4.507346914},
{"learn":[0.06726996922],"iteration":816,"passed_time":20.01408818,"remaining_time":4.482959776},
{"learn":[0.06722582843],"iteration":817,"passed_time":20.03807534,"remaining_time":4.45834928},
{"learn":[0.0671798146],"iteration":818,"passed_time":20.06406933,"remaining_time":4.434183819},
{"learn":[0.06713426635],"iteration":819,"passed_time":20.08858624,"remaining_time":4.409689662},
{"learn":[0.06708123799],"iteration":820,"passed_time":20.11373846,"remaining_time":4.385333964},
{"learn":[0.0670467898],"iteration":821,"passed_time":20.13697808,"remaining_time":4.360562164},
{"learn":[0.066991967],"iteration":822,"passed_time":20.16046674,"remaining_time":4.335847646},
{"learn":[0.06695225419],"iteration":823,"passed_time":20.18470842,"remaining_time":4.311296944},
{"learn":[0.06690110474],"iteration":824,"passed_time":20.20881925,"remaining_time":4.286719235},
{"learn":[0.06684302939],"iteration":825,"passed_time":20.23360977,"remaining_time":4.262285835},
{"learn":[0.06680180667],"iteration":826,"passed_time":20.25665535,"remaining_time":4.237486549},
{"learn":[0.06677303766],"iteration":827,"passed_time":20.28186118,"remaining_time":4.213140245},
{"learn":[0.06672181924],"iteration":828,"passed_time":20.30629379,"remaining_time":4.188632373},
{"learn":[0.06668638436],"iteration":829,"passed_time":20.33124443,"remaining_time":4.164230786},
{"learn":[0.0666127325],"iteration":830,"passed_time":20.35497323,"remaining_time":4.139579394},
{"learn":[0.06651863381],"iteration":831,"passed_time":20.37788031,"remaining_time":4.114764293},
{"learn":[0.06644742874],"iteration":832,"passed_time":20.40261279,"remaining_time":4.090319731},
{"learn":[0.06639995512],"iteration":833,"passed_time":20.42690759,"remaining_time":4.065787363},
{"learn":[0.06635124896],"iteration":834,"passed_time":20.45066423,"remaining_time":4.041149219},
{"learn":[0.06630823145],"iteration":835,"passed_time":20.47336429,"remaining_time":4.016305913},
{"learn":[0.06627138859],"iteration":836,"passed_time":20.49678477,"remaining_time":3.991608026},
{"learn":[0.06619997144],"iteration":837,"passed_time":20.52143719,"remaining_time":3.967151343},
{"learn":[0.0661674784],"iteration":838,"passed_time":20.54368648,"remaining_time":3.942233044},
{"learn":[0.06613462453],"iteration":839,"passed_time":20.56789567,"remaining_time":3.917694413},
{"learn":[0.06610083491],"iteration":840,"passed_time":20.59247637,"remaining_time":3.893226805},
{"learn":[0.06603300688],"iteration":841,"passed_time":20.61739546,"remaining_time":3.868822425},
{"learn":[0.06598151061],"iteration":842,"passed_time":20.64138359,"remaining_time":3.844243445},
{"learn":[0.06593458647],"iteration":843,"passed_time":20.66452962,"remaining_time":3.819510214},
{"learn":[0.06590172743],"iteration":844,"passed_time":20.68864046,"remaining_time":3.794957717},
{"learn":[0.06582366638],"iteration":845,"passed_time":20.71484137,"remaining_time":3.770786726},
{"learn":[0.0657851385],"iteration":846,"passed_time":20.73717764,"remaining_time":3.745912844},
{"learn":[0.06575514633],"iteration":847,"passed_time":20.75911606,"remaining_time":3.720973633},
{"learn":[0.06570834967],"iteration":848,"passed_time":20.78298096,"remaining_time":3.696384129},
{"learn":[0.06565343187],"iteration":849,"passed_time":20.80602338,"remaining_time":3.671651185},
{"learn":[0.0656066077],"iteration":850,"passed_time":20.83135903,"remaining_time":3.647323731},
{"learn":[0.06556446781],"iteration":851,"passed_time":20.85622619,"remaining_time":3.62291253},
{"learn":[0.06553720049],"iteration":852,"passed_time":20.87854786,"remaining_time":3.598061588},
{"learn":[0.06550664519],"iteration":853,"passed_time":20.90112648,"remaining_time":3.573260499},
{"learn":[0.06545381988],"iteration":854,"passed_time":20.92665567,"remaining_time":3.548964996},
{"learn":[0.06537061337],"iteration":855,"passed_time":20.95036266,"remaining_time":3.524360073},
{"learn":[0.065319165],"iteration":856,"passed_time":20.9737601,"remaining_time":3.499705595},
{"learn":[0.06525013312],"iteration":857,"passed_time":20.99781447,"remaining_time":3.475162767},
{"learn":[0.06518576957],"iteration":858,"passed_time":21.02382356,"remaining_time":3.450941935},
{"learn":[0.06512719272],"iteration":859,"passed_time":21.04918593,"remaining_time":3.426611664},
{"learn":[0.06507363336],"iteration":860,"passed_time":21.07312684,"remaining_time":3.402049512},
{"learn":[0.06499787246],"iteration":861,"passed_time":21.09969797,"remaining_time":3.377909884},
{"learn":[0.06494315317],"iteration":862,"passed_time":21.12451475,"remaining_time":3.35348612},
{"learn":[0.06488219567],"iteration":863,"passed_time":21.15036526,"remaining_time":3.329224162},
{"learn":[0.06484639056],"iteration":864,"passed_time":21.17361846,"remaining_time":3.30455317},
{"learn":[0.06480887016],"iteration":865,"passed_time":21.1962594,"remaining_time":3.279790716},
{"learn":[0.06476695743],"iteration":866,"passed_time":21.22256848,"remaining_time":3.255595856},
{"learn":[0.06468242472],"iteration":867,"passed_time":21.247743,"remaining_time":3.23122359},
{"learn":[0.06461854296],"iteration":868,"passed_time":21.27180309,"remaining_time":3.206681479},
{"learn":[0.06456318371],"iteration":869,"passed_time":21.29676423,"remaining_time":3.182275115},
{"learn":[0.06450437197],"iteration":870,"passed_time":21.3225021,"remaining_time":3.157982515},
{"learn":[0.06445463618],"iteration":871,"passed_time":21.34589592,"remaining_time":3.13334252},
{"learn":[0.064415725],"iteration":872,"passed_time":21.3687639,"remaining_time":3.108628884},
{"learn":[0.06437156138],"iteration":873,"passed_time":21.39413553,"remaining_time":3.084280408},
{"learn":[0.06434242604],"iteration":874,"passed_time":21.4188501,"remaining_time":3.059835728},
{"learn":[0.0642500169],"iteration":875,"passed_time":21.4446055,"remaining_time":3.035537764},
{"learn":[0.06419316266],"iteration":876,"passed_time":21.47371853,"remaining_time":3.011707388},
{"learn":[0.06413081531],"iteration":877,"passed_time":21.49924593,"remaining_time":2.987366746},
{"learn":[0.06410184804],"iteration":878,"passed_time":21.52147572,"remaining_time":2.962569467},
{"learn":[0.06405931234],"iteration":879,"passed_time":21.54541865,"remaining_time":2.938011633},
{"learn":[0.06397870715],"iteration":880,"passed_time":21.57048345,"remaining_time":2.913606732},
{"learn":[0.06391294163],"iteration":881,"passed_time":21.5938341,"remaining_time":2.888971003},
{"learn":[0.06388006709],"iteration":882,"passed_time":21.61800598,"remaining_time":2.864446998},
{"learn":[0.06382038225],"iteration":883,"passed_time":21.63947097,"remaining_time":2.839568588},
{"learn":[0.06377748717],"iteration":884,"passed_time":21.6634605,"remaining_time":2.815025941},
{"learn":[0.06369990242],"iteration":885,"passed_time":21.68830344,"remaining_time":2.790594348},
{"learn":[0.06365428575],"iteration":886,"passed_time":21.71216552,"remaining_time":2.76603687},
{"learn":[0.06358535762],"iteration":887,"passed_time":21.73675869,"remaining_time":2.741573168},
{"learn":[0.06355133322],"iteration":888,"passed_time":21.75997422,"remaining_time":2.716937164},
{"learn":[0.06351569557],"iteration":889,"passed_time":21.78456675,"remaining_time":2.692474542},
{"learn":[0.06346573857],"iteration":890,"passed_time":21.80879051,"remaining_time":2.667966516},
{"learn":[0.06342946565],"iteration":891,"passed_time":21.83037193,"remaining_time":2.643139203},
{"learn":[0.063371494],"iteration":892,"passed_time":21.85347706,"remaining_time":2.61850173},
{"learn":[0.06334283523],"iteration":893,"passed_time":21.87623077,"remaining_time":2.593826019},
{"learn":[0.06330211836],"iteration":894,"passed_time":21.89893086,"remaining_time":2.569148313},
{"learn":[0.06324929513],"iteration":895,"passed_time":21.92459521,"remaining_time":2.544819087},
{"learn":[0.06321475223],"iteration":896,"passed_time":21.95030152,"remaining_time":2.520491701},
{"learn":[0.06318834794],"iteration":897,"passed_time":21.97324763,"remaining_time":2.495847727},
{"learn":[0.06312789466],"iteration":898,"passed_time":21.99958988,"remaining_time":2.471589074},
{"learn":[0.06308913977],"iteration":899,"passed_time":22.02318575,"remaining_time":2.447020639},
{"learn":[0.06304852329],"iteration":900,"passed_time":22.04687332,"remaining_time":2.422464438},
{"learn":[0.06299671702],"iteration":901,"passed_time":22.07185083,"remaining_time":2.398050312},
{"learn":[0.06295033374],"iteration":902,"passed_time":22.09715776,"remaining_time":2.373670324},
{"learn":[0.06291321953],"iteration":903,"passed_time":22.12106081,"remaining_time":2.349139202},
{"learn":[0.06286418519],"iteration":904,"passed_time":22.14418596,"remaining_time":2.324527808},
{"learn":[0.06282289298],"iteration":905,"passed_time":22.16760968,"remaining_time":2.299950673},
{"learn":[0.06277073126],"iteration":906,"passed_time":22.19431215,"remaining_time":2.275712271},
{"learn":[0.06271094769],"iteration":907,"passed_time":22.21809639,"remaining_time":2.251172762},
{"learn":[0.06263708405],"iteration":908,"passed_time":22.24296064,"remaining_time":2.226743034},
{"learn":[0.06259172422],"iteration":909,"passed_time":22.26999549,"remaining_time":2.202527027},
{"learn":[0.06255631418],"iteration":910,"passed_time":22.29416398,"remaining_time":2.178024801},
{"learn":[0.06253627913],"iteration":911,"passed_time":22.31867606,"remaining_time":2.153556462},
{"learn":[0.06248650865],"iteration":912,"passed_time":22.3429188,"remaining_time":2.129062361},
{"learn":[0.06246844157],"iteration":913,"passed_time":22.36488263,"remaining_time":2.104354383},
{"learn":[0.06242952811],"iteration":914,"passed_time":22.38890099,"remaining_time":2.079843261},
{"learn":[0.06236847457],"iteration":915,"passed_time":22.41261203,"remaining_time":2.055305033},
{"learn":[0.06234084727],"iteration":916,"passed_time":22.4368464,"remaining_time":2.030815977},
{"learn":[0.06228015346],"iteration":917,"passed_time":22.45958895,"remaining_time":2.00619422},
{"learn":[0.06225177623],"iteration":918,"passed_time":22.48197087,"remaining_time":1.981544767},
{"learn":[0.06220240903],"iteration":919,"passed_time":22.50659583,"remaining_time":1.95709529},
{"learn":[0.06213452841],"iteration":920,"passed_time":22.53238999,"remaining_time":1.932745721},
{"learn":[0.06207702316],"iteration":921,"passed_time":22.5559712,"remaining_time":1.908205807},
{"learn":[0.06204767726],"iteration":922,"passed_time":22.5792564,"remaining_time":1.883643275},
{"learn":[0.0620173819],"iteration":923,"passed_time":22.60126575,"remaining_time":1.858978568},
{"learn":[0.06197267436],"iteration":924,"passed_time":22.62404806,"remaining_time":1.834382275},
{"learn":[0.06194461305],"iteration":925,"passed_time":22.64837257,"remaining_time":1.809913143},
{"learn":[0.06189574263],"iteration":926,"passed_time":22.67347322,"remaining_time":1.785505443},
{"learn":[0.06185198101],"iteration":927,"passed_time":22.69563116,"remaining_time":1.760867935},
{"learn":[0.06180891163],"iteration":928,"passed_time":22.72224016,"remaining_time":1.736575943},
{"learn":[0.06175521464],"iteration":929,"passed_time":22.7463871,"remaining_time":1.712093653},
{"learn":[0.06168583063],"iteration":930,"passed_time":22.7689717,"remaining_time":1.687496292},
{"learn":[0.06163014796],"iteration":931,"passed_time":22.7944524,"remaining_time":1.663114553},
{"learn":[0.06159069368],"iteration":932,"passed_time":22.81678251,"remaining_time":1.63850421},
{"learn":[0.06154520674],"iteration":933,"passed_time":22.84200935,"remaining_time":1.614103444},
{"learn":[0.06147731458],"iteration":934,"passed_time":22.86730694,"remaining_time":1.58970583},
{"learn":[0.06143553063],"iteration":935,"passed_time":22.8913157,"remaining_time":1.565218168},
{"learn":[0.06140169409],"iteration":936,"passed_time":22.91611256,"remaining_time":1.540784516},
{"learn":[0.06135953312],"iteration":937,"passed_time":22.94015851,"remaining_time":1.516300456},
{"learn":[0.06131187723],"iteration":938,"passed_time":22.96268193,"remaining_time":1.491718421},
{"learn":[0.06128542187],"iteration":939,"passed_time":22.99610092,"remaining_time":1.467836229},
{"learn":[0.06124533233],"iteration":940,"passed_time":23.02194753,"remaining_time":1.443458984},
{"learn":[0.06120702079],"iteration":941,"passed_time":23.04634868,"remaining_time":1.418989621},
{"learn":[0.06115982603],"iteration":942,"passed_time":23.06962156,"remaining_time":1.394452204},
{"learn":[0.06113529453],"iteration":943,"passed_time":23.09382669,"remaining_time":1.36997277},
{"learn":[0.06107659658],"iteration":944,"passed_time":23.11865945,"remaining_time":1.345530444},
{"learn":[0.06102812454],"iteration":945,"passed_time":23.14043454,"remaining_time":1.320912754},
{"learn":[0.06097852253],"iteration":946,"passed_time":23.16287861,"remaining_time":1.296338507},
{"learn":[0.06095021325],"iteration":947,"passed_time":23.18546902,"remaining_time":1.271776782},
{"learn":[0.06089617284],"iteration":948,"passed_time":23.20957603,"remaining_time":1.247300714},
{"learn":[0.06085252084],"iteration":949,"passed_time":23.23395428,"remaining_time":1.222839699},
{"learn":[0.06081320881],"iteration":950,"passed_time":23.25783328,"remaining_time":1.198353134},
{"learn":[0.06076310852],"iteration":951,"passed_time":23.28397771,"remaining_time":1.17398207},
{"learn":[0.06068267408],"iteration":952,"passed_time":23.30868268,"remaining_time":1.149536292},
{"learn":[0.06064423822],"iteration":953,"passed_time":23.33128681,"remaining_time":1.124988672},
{"learn":[0.06060157547],"iteration":954,"passed_time":23.3552023,"remaining_time":1.100506914},
{"learn":[0.06054928047],"iteration":955,"passed_time":23.37996718,"remaining_time":1.076065435},
{"learn":[0.06048721509],"iteration":956,"passed_time":23.40609397,"remaining_time":1.051684473},
{"learn":[0.06044802398],"iteration":957,"passed_time":23.42947402,"remaining_time":1.027179445},
{"learn":[0.06039732688],"iteration":958,"passed_time":23.45485055,"remaining_time":1.002762119},
{"learn":[0.06034238241],"iteration":959,"passed_time":23.4794184,"remaining_time":0.9783090998},
{"learn":[0.06030509229],"iteration":960,"passed_time":23.50476151,"remaining_time":0.9538873037},
{"learn":[0.06025101095],"iteration":961,"passed_time":23.52968361,"remaining_time":0.9294469619},
{"learn":[0.06020805644],"iteration":962,"passed_time":23.55581511,"remaining_time":0.9050520863},
{"learn":[0.06012103393],"iteration":963,"passed_time":23.58053471,"remaining_time":0.8806008813},
{"learn":[0.06008210406],"iteration":964,"passed_time":23.60388418,"remaining_time":0.8560994263},
{"learn":[0.06005326392],"iteration":965,"passed_time":23.6288835,"remaining_time":0.8316584256},
{"learn":[0.05998037578],"iteration":966,"passed_time":23.6551658,"remaining_time":0.807260053},
{"learn":[0.05992365929],"iteration":967,"passed_time":23.68117695,"remaining_time":0.7828488249},
{"learn":[0.05986667883],"iteration":968,"passed_time":23.70600274,"remaining_time":0.7583963725},
{"learn":[0.05981335231],"iteration":969,"passed_time":23.73220425,"remaining_time":0.7339856983},
{"learn":[0.05976783528],"iteration":970,"passed_time":23.75570954,"remaining_time":0.7094908102},
{"learn":[0.05970485849],"iteration":971,"passed_time":23.78041866,"remaining_time":0.6850326364},
{"learn":[0.0596608458],"iteration":972,"passed_time":23.80333966,"remaining_time":0.6605243277},
{"learn":[0.05961063873],"iteration":973,"passed_time":23.82897226,"remaining_time":0.6360916619},
{"learn":[0.05956973246],"iteration":974,"passed_time":23.85346026,"remaining_time":0.6116271861},
{"learn":[0.05954311343],"iteration":975,"passed_time":23.88083127,"remaining_time":0.5872335559},
{"learn":[0.05946262418],"iteration":976,"passed_time":23.90886414,"remaining_time":0.5628494117},
{"learn":[0.05942569103],"iteration":977,"passed_time":23.93367422,"remaining_time":0.5383853097},
{"learn":[0.05935750686],"iteration":978,"passed_time":23.95974664,"remaining_time":0.5139475786},
{"learn":[0.05931527893],"iteration":979,"passed_time":23.98403145,"remaining_time":0.4894700296},
{"learn":[0.05922544343],"iteration":980,"passed_time":24.00956222,"remaining_time":0.4650170052},
{"learn":[0.05918402057],"iteration":981,"passed_time":24.03340046,"remaining_time":0.440530762},
{"learn":[0.05912874147],"iteration":982,"passed_time":24.05732897,"remaining_time":0.4160473982},
{"learn":[0.05906389796],"iteration":983,"passed_time":24.07984956,"remaining_time":0.3915422692},
{"learn":[0.05902923058],"iteration":984,"passed_time":24.10438897,"remaining_time":0.3670719133},
{"learn":[0.05899486143],"iteration":985,"passed_time":24.1272709,"remaining_time":0.342577883},
{"learn":[0.05896666663],"iteration":986,"passed_time":24.15255735,"remaining_time":0.3181187898},
{"learn":[0.05893039246],"iteration":987,"passed_time":24.17520868,"remaining_time":0.2936260164},
{"learn":[0.05883852697],"iteration":988,"passed_time":24.20061174,"remaining_time":0.2691675724},
{"learn":[0.05878813737],"iteration":989,"passed_time":24.22453817,"remaining_time":0.2446923047},
{"learn":[0.05873644781],"iteration":990,"passed_time":24.24893739,"remaining_time":0.2202224384},
{"learn":[0.05866949935],"iteration":991,"passed_time":24.27254397,"remaining_time":0.1957463224},
{"learn":[0.05862110338],"iteration":992,"passed_time":24.29747462,"remaining_time":0.1712812913},
{"learn":[0.05857304373],"iteration":993,"passed_time":24.32252994,"remaining_time":0.1468160761},
{"learn":[0.05851777062],"iteration":994,"passed_time":24.34574902,"remaining_time":0.1223404473},
{"learn":[0.05848658258],"iteration":995,"passed_time":24.36855837,"remaining_time":0.09786569628},
{"learn":[0.05843631223],"iteration":996,"passed_time":24.39279035,"remaining_time":0.07339856676},
{"learn":[0.05839472806],"iteration":997,"passed_time":24.4180895,"remaining_time":0.04893404709},
{"learn":[0.05836232232],"iteration":998,"passed_time":24.44193176,"remaining_time":0.02446639815},
{"learn":[0.05831147394],"iteration":999,"passed_time":24.46730887,"remaining_time":0}
]}